{"skeleton":{"hash":"7ntTDU8g7PnZuoqHe8KrJxEChmQ","spine":"3.8.72","images":"./images/","audio":"C:/設計區/胖達專案區/多福多財/4_動態特效/SPINE/EditFiles/Item_Megawin"},"bones":[{"name":"root","scaleX":0.75,"scaleY":0.75},{"name":"All","parent":"root","color":"ff0000ff"},{"name":"2_WIN","parent":"All","color":"0047ffff"},{"name":"1_MEGA","parent":"All","y":176.74,"color":"8300ffff"},{"name":"3_Left_gold","parent":"All","rotation":18.38,"x":-271.34,"y":-70.15,"color":"e6ff00ff"},{"name":"4_Right_gold","parent":"All","rotation":-11.53,"x":295.73,"y":-76.44,"color":"f7ff00ff"},{"name":"6_Right_SMZ","parent":"All","rotation":-72.88,"x":242.31,"y":-74.46,"color":"ff0000ff"},{"name":"骨骼5","parent":"6_Right_SMZ","length":180.29,"rotation":172.59,"x":-16.16,"y":8.03,"color":"ff0000ff"},{"name":"骨骼6","parent":"6_Right_SMZ","length":174.2,"rotation":60.17,"x":13.82,"y":14.14,"color":"ff0000ff"},{"name":"7_Left_pao","parent":"All","length":103.09,"rotation":110.51,"x":-281.86,"y":-86.08,"color":"ff0000ff"},{"name":"All3","parent":"7_Left_pao","length":89.22,"rotation":0.64,"x":103.09,"color":"ff0000ff"},{"name":"All4","parent":"All3","length":53.36,"rotation":5.04,"x":89.22,"color":"ff0000ff"},{"name":"All5","parent":"All4","length":31.64,"rotation":-19.06,"x":53.36,"color":"ff0000ff"},{"name":"All6","parent":"All5","length":35.08,"rotation":33.34,"x":31.64,"color":"ff0000ff"},{"name":"All7","parent":"All6","length":25.63,"rotation":9.51,"x":35.08,"color":"ff0000ff"},{"name":"8_Right_pao","parent":"All","length":121.45,"rotation":67.6,"x":282.67,"y":-80.07,"color":"ff0000ff"},{"name":"All9","parent":"8_Right_pao","length":90.41,"rotation":1.61,"x":121.45,"color":"ff0000ff"},{"name":"All10","parent":"All9","length":49.74,"rotation":-2.6,"x":90.41,"color":"ff0000ff"},{"name":"All11","parent":"All10","length":32.02,"rotation":-1.7,"x":49.74,"color":"ff0000ff"},{"name":"All12","parent":"All11","length":30.74,"rotation":14.68,"x":32.02,"color":"ff0000ff"},{"name":"All13","parent":"All12","length":30.86,"rotation":-1.13,"x":30.74,"color":"ff0000ff"},{"name":"Light_All","parent":"All","color":"faff00ff"},{"name":"MEGA_Seq","parent":"1_MEGA","x":1.92,"y":-19.39,"scaleX":2,"scaleY":2,"color":"8300ffff"},{"name":"WIN_Seq","parent":"2_WIN","x":9.97,"y":7.98,"scaleX":2,"scaleY":2,"color":"0047ffff"},{"name":"FireSeq","parent":"Light_All","color":"faff00ff"},{"name":"Icon_Common_24","parent":"Light_All","color":"faff00ff"},{"name":"glow","parent":"Light_All","color":"faff00ff"},{"name":"fangshe02","parent":"Light_All","color":"faff00ff"},{"name":"RedLig","parent":"Light_All","color":"ff0000ff"},{"name":"RedLig2","parent":"Light_All","color":"ff0000ff"},{"name":"RedLig3","parent":"Light_All","color":"ff0000ff"},{"name":"RedLig4","parent":"Light_All","color":"ff0000ff"},{"name":"LigDot_Left","parent":"All","x":-193.68,"y":-21.65,"color":"ff0000ff"},{"name":"LigDot_Right","parent":"All","x":197.29,"y":-21.65,"color":"ff0000ff"},{"name":"5_Left_SMZ2","parent":"All","rotation":15.04,"x":-256.5,"y":-106.02,"color":"ff0000ff"},{"name":"骨骼7","parent":"5_Left_SMZ2","length":180.29,"rotation":172.59,"x":-16.16,"y":8.03,"color":"ff0000ff"},{"name":"骨骼8","parent":"5_Left_SMZ2","length":174.2,"rotation":60.17,"x":13.82,"y":14.14,"color":"ff0000ff"},{"name":"SPARK_Lrft","parent":"All7","rotation":-139.97,"x":-2.23,"y":6.12,"color":"ff0000ff"},{"name":"SPARK_Lrft2","parent":"SPARK_Lrft","color":"ff0000ff"},{"name":"SPARK_Lrft3","parent":"SPARK_Lrft","color":"ff0000ff"},{"name":"骨骼2","parent":"All13","x":-8.63,"y":0.35,"color":"ff0000ff"},{"name":"骨骼3","parent":"骨骼2","color":"ff0000ff"}],"slots":[{"name":"glow","bone":"glow","blend":"additive"},{"name":"RedLig2","bone":"RedLig2","blend":"additive"},{"name":"RedLig","bone":"RedLig","blend":"additive"},{"name":"Jew03","bone":"All"},{"name":"Jew02","bone":"All"},{"name":"Jew01","bone":"All"},{"name":"SMZ02","bone":"All"},{"name":"SMZ01","bone":"All"},{"name":"GF02","bone":"LigDot_Right","blend":"screen"},{"name":"GF01","bone":"LigDot_Left","blend":"screen"},{"name":"firecrB","bone":"All"},{"name":"firecrA","bone":"All"},{"name":"sparkB","bone":"骨骼2"},{"name":"sparkB2","bone":"骨骼3","blend":"additive"},{"name":"sparkA","bone":"SPARK_Lrft"},{"name":"sparkA2","bone":"SPARK_Lrft2","blend":"additive"},{"name":"sparkA3","bone":"SPARK_Lrft3","blend":"additive"},{"name":"BAO_Left","bone":"3_Left_gold"},{"name":"BAO_Right","bone":"4_Right_gold"},{"name":"1_MEGA","bone":"1_MEGA"},{"name":"1_MEGA2","bone":"1_MEGA","blend":"additive"},{"name":"2_WIN","bone":"2_WIN"},{"name":"2_WIN2","bone":"2_WIN","blend":"additive"},{"name":"Icon_Common_24","bone":"Icon_Common_24","blend":"additive"},{"name":"fangshe02","bone":"fangshe02","blend":"additive"},{"name":"MEGA_Seq","bone":"MEGA_Seq","blend":"additive"},{"name":"WIN_Seq","bone":"WIN_Seq","blend":"additive"},{"name":"FireSeq","bone":"FireSeq","blend":"additive"},{"name":"RedLig3","bone":"RedLig3","blend":"additive"},{"name":"RedLig4","bone":"RedLig4","blend":"additive"}],"skins":[{"name":"default","attachments":{"1_MEGA":{"MEGA":{"x":1.5,"y":-19.74,"width":649,"height":168}},"SMZ01":{"SMZ01":{"type":"mesh","uvs":[0.4362,0,0.59733,0.06873,0.75846,0.13745,0.87381,0.34456,0.98916,0.55166,0.99458,0.71902,1,0.88639,1,1,0.9523,1,0.84106,0.96496,0.59192,0.89474,0.46735,0.85963,0.34278,0.82453,0.25708,0.65555,0.17139,0.48657,0.08569,0.31758,0,0.1486,0,0.13542,0.04657,0.07873,0.28091,0,0.38691,0.42482,0.63133,0.5765,0.50032,0.22921,0.82121,0.70312,0.25999,0.19561,0.44202,0.67512,0.63017,0.34246,0.77152,0.54069,0.68321,0.72585,0.91305,0.77603,0.27686,0.38476,0.5182,0.44962,0.35693,0.20563,0.75848,0.34118,0.76976,0.81308],"triangles":[3,33,2,27,33,3,27,3,4,27,21,26,27,26,33,25,31,21,23,27,4,23,4,5,28,21,27,28,27,23,29,23,5,34,28,23,34,23,29,25,10,11,28,25,21,12,25,11,29,5,6,28,10,25,10,28,34,9,34,29,9,29,6,10,34,9,8,9,6,8,6,7,16,17,18,24,18,19,32,19,0,24,19,32,22,0,1,32,0,22,15,18,24,16,18,15,26,1,2,26,2,33,22,1,26,30,24,32,15,24,30,20,32,22,30,32,20,31,22,26,20,22,31,14,15,30,31,26,21,13,14,30,13,30,20,25,20,31,13,20,25,12,13,25],"vertices":[2,7,166.74,-61.1,0.94994,8,-27.31,200.4,0.05006,2,7,140.38,-109.55,0.80345,8,27.53,194.51,0.19655,2,7,114.03,-158.01,0.62616,8,82.38,188.63,0.37384,2,7,54.85,-185.8,0.37733,8,130.63,144.52,0.62267,2,7,-4.32,-213.59,0.14616,8,178.88,100.42,0.85384,2,7,-47.35,-208,0.05482,8,190.13,58.52,0.94518,2,7,-90.37,-202.42,0.00422,8,201.38,16.61,0.99578,1,8,207.85,-12.09,1,1,8,192.77,-15.49,1,1,8,155.61,-14.56,1,1,8,72.87,-14.57,1,1,8,31.5,-14.58,1,2,6,21.55,-1.68,0.33049,8,-9.88,-14.58,0.66951,2,6,-28.45,-15.32,0.12509,7,9.18,24.75,0.87491,1,7,57,44.73,1,1,7,104.82,64.71,1,1,7,152.64,84.69,1,1,7,156.01,84.12,1,1,7,167.94,66.77,1,2,7,175.23,-11.51,0.99807,8,-76.39,189.33,0.00193,2,7,60.98,-26.8,0.93672,8,-18.69,89.55,0.06328,2,7,8.9,-98.23,0.34252,8,67.2,68.64,0.65748,2,7,104.72,-71.56,0.85372,8,6.01,147.06,0.14628,2,7,-33.81,-153.33,0.08293,8,134.43,50.18,0.91707,1,7,126.43,3.72,1,2,7,-5.93,-33.46,0.45674,8,12.98,30.24,0.54326,2,7,68.71,-108.08,0.62374,8,53.5,127.69,0.37626,2,7,10.38,-144.56,0.26253,8,109.47,87.68,0.73747,2,7,-32.07,-108.27,0.08984,8,92.1,34.61,0.91016,2,7,-57.44,-179.47,0.03231,8,167.61,38.3,0.96769,1,7,77.22,6.6,1,2,7,47.47,-67.64,0.69677,8,24.22,92.64,0.30323,2,7,118.57,-26.8,0.97823,8,-40.65,142.8,0.02177,2,7,62.02,-149.11,0.481,8,93.99,137.16,0.519,2,7,-59.07,-132.09,0.01843,8,124.43,18.73,0.98157],"hull":20,"edges":[0,2,2,4,4,6,6,8,8,10,10,12,12,14,14,16,16,18,18,20,20,22,22,24,24,26,26,28,28,30,30,32,32,34,34,36,36,38,38,0],"width":324,"height":259}},"SMZ02":{"SMZ02":{"type":"mesh","uvs":[0.77486,0,1,0.10114,1,0.13011,0.91698,0.29897,0.83396,0.46784,0.75095,0.6367,0.66793,0.80556,0.51218,0.85417,0.35642,0.90278,0.20067,0.95139,0.04492,1,0.02979,1,0,0.90937,0,0.73568,0.03236,0.56385,0.06472,0.39202,0.21272,0.22411,0.36073,0.05621,0.64962,0,0.33018,0.58597,0.56366,0.32449,0.32956,0.34244,0.51363,0.57151,0.81957,0.18906,0.13286,0.75428,0.52329,0.20023,0.46711,0.71653,0.71194,0.277,0.675,0.45592,0.27281,0.75184,0.21755,0.42905,0.48906,0.41342,0.15008,0.60156],"triangles":[9,10,12,10,11,12,12,24,9,9,29,8,9,24,29,12,13,24,8,26,7,8,29,26,7,26,6,26,22,6,6,22,5,24,32,29,24,13,32,29,19,26,29,32,19,13,14,32,26,19,22,22,28,5,5,28,4,14,15,32,32,30,19,32,15,30,30,21,19,19,31,22,19,21,31,28,31,20,28,22,31,28,27,4,4,27,3,3,27,23,28,20,27,15,16,30,30,16,21,20,31,25,31,21,25,21,17,25,21,16,17,20,25,27,3,23,2,25,18,27,23,18,0,23,27,18,25,17,18,2,23,1,23,0,1],"vertices":[1,34,90.52,199.36,1,1,34,152.92,154.84,1,1,34,150.93,147.42,1,1,34,113.74,111.08,1,1,34,76.55,74.74,1,1,34,39.37,38.39,1,1,34,2.18,2.05,1,1,34,-49.15,2.51,1,1,34,-100.48,2.96,1,1,34,-151.8,3.41,1,1,34,-203.13,3.87,1,1,34,-207.79,5.12,1,1,34,-210.73,30.78,1,1,34,-198.79,75.23,1,1,34,-177,116.53,1,1,34,-155.21,157.83,1,1,34,-98.07,188.54,1,1,34,-40.93,219.26,1,1,34,51.94,209.73,1,1,34,-86.77,86.21,1,1,34,3.14,133.8,1,1,34,-70.21,148.59,1,1,34,-29.26,74.72,1,1,34,91.29,147.27,1,1,34,-159.14,59.47,1,1,34,-0.75,168.94,1,1,34,-53.57,41.46,1,1,34,52.09,133.68,1,1,34,28.4,90.95,1,1,34,-115.85,48.51,1,1,34,-110.68,135.69,1,1,34,-25.96,117.22,1,1,34,-143.33,97.13,1],"hull":19,"edges":[0,2,2,4,4,6,6,8,8,10,10,12,12,14,14,16,16,18,18,20,20,22,22,24,24,26,26,28,28,30,30,32,32,34,34,36,36,0],"width":319,"height":265}},"WIN_Seq":{"WIN_Seq/Comp 1_00000":{"width":228,"height":90},"WIN_Seq/Comp 1_00001":{"width":228,"height":90},"WIN_Seq/Comp 1_00002":{"width":228,"height":90},"WIN_Seq/Comp 1_00003":{"width":228,"height":90},"WIN_Seq/Comp 1_00004":{"width":228,"height":90},"WIN_Seq/Comp 1_00005":{"width":228,"height":90},"WIN_Seq/Comp 1_00006":{"width":228,"height":90},"WIN_Seq/Comp 1_00007":{"width":228,"height":90},"WIN_Seq/Comp 1_00008":{"width":228,"height":90},"WIN_Seq/Comp 1_00009":{"width":228,"height":90},"WIN_Seq/Comp 1_00010":{"width":228,"height":90},"WIN_Seq/Comp 1_00011":{"width":228,"height":90},"WIN_Seq/Comp 1_00012":{"width":228,"height":90},"WIN_Seq/Comp 1_00013":{"width":228,"height":90},"WIN_Seq/Comp 1_00014":{"width":228,"height":90},"WIN_Seq/Comp 1_00015":{"width":228,"height":90},"WIN_Seq/Comp 1_00016":{"width":228,"height":90},"WIN_Seq/Comp 1_00017":{"width":228,"height":90},"WIN_Seq/Comp 1_00018":{"width":228,"height":90},"WIN_Seq/Comp 1_00019":{"width":228,"height":90},"WIN_Seq/Comp 1_00020":{"width":228,"height":90},"WIN_Seq/Comp 1_00021":{"width":228,"height":90},"WIN_Seq/Comp 1_00022":{"width":228,"height":90},"WIN_Seq/Comp 1_00023":{"width":228,"height":90},"WIN_Seq/Comp 1_00024":{"width":228,"height":90},"WIN_Seq/Comp 1_00025":{"width":228,"height":90},"WIN_Seq/Comp 1_00026":{"width":228,"height":90},"WIN_Seq/Comp 1_00027":{"width":228,"height":90},"WIN_Seq/Comp 1_00028":{"width":228,"height":90}},"sparkA":{"sparkA":{"type":"mesh","uvs":[0.65205,0.07424,0.7316,0.15714,0.75557,0.24847,0.84073,0.29714,0.86302,0.30359,0.9489,0.46105,0.94349,0.57993,0.87144,0.65505,0.79939,0.73017,0.69533,0.82685,0.64045,0.83478,0.60843,0.91891,0.5169,0.89616,0.5005,1,0.47696,1,0.41182,0.86496,0.36931,0.86961,0.28534,0.81547,0.2887,0.76881,0.1819,0.65605,0.16928,0.70819,0.11489,0.62333,0.11428,0.49834,0.12118,0.39839,0.12809,0.29844,0.22387,0.22889,0.31964,0.15934,0.33231,0.12316,0.34155,0.07682,0.3813,0.1323,0.45623,0.06062,0.45247,0,0.45997,0,0.47596,0.01657,0.43926,0.32484,0.83039,0.45826,0.44873,0.70429,0.65904,0.589,0.29641,0.5786,0.62333,0.29874,0.45901,0.47709,0.28331,0.36657,0.70994,0.42025,0.62642,0.76319,0.51043,0.17823,0.80218,0.57223],"triangles":[18,19,38,20,21,19,38,19,22,19,21,22,38,22,41,22,23,41,38,41,40,41,34,40,40,34,39,23,24,41,41,26,34,26,29,34,26,27,29,24,25,41,41,25,26,34,44,39,34,29,44,39,0,1,39,44,0,29,30,44,44,30,0,0,30,33,27,28,29,33,31,32,33,30,31,36,40,37,36,38,40,37,42,45,37,40,42,6,35,5,45,42,35,40,39,42,35,4,5,35,3,4,35,42,3,42,2,3,42,39,2,39,1,2,15,16,18,16,17,18,43,12,36,12,15,36,15,18,36,9,43,8,18,38,36,43,37,8,43,36,37,8,45,7,8,37,45,7,45,6,45,35,6,13,14,12,14,15,12,11,12,10,10,12,43,10,43,9],"vertices":[3,12,118.71,-18.03,8.8E-4,13,62.83,-62.91,0.32632,14,16.98,-66.63,0.67281,3,12,103.26,-30.05,0.01584,13,43.32,-64.46,0.4711,14,-2.52,-64.93,0.51305,3,12,87.61,-32.29,0.07525,13,29.01,-57.73,0.61987,14,-15.53,-55.94,0.30488,3,12,77.7,-45.99,0.20925,13,13.21,-63.73,0.68396,14,-32.1,-59.24,0.10679,3,12,76.15,-49.7,0.23052,13,9.87,-65.98,0.67991,14,-35.76,-60.91,0.08957,3,12,48.21,-61.27,0.46368,13,-19.83,-60.29,0.52848,14,-64.12,-50.39,0.00783,4,11,61.52,-64.05,5.4E-4,12,28.62,-57.87,0.59654,13,-34.33,-46.69,0.4029,14,-76.17,-34.58,2.0E-5,3,11,55.79,-47.26,0.01327,12,17.73,-43.88,0.72879,13,-35.74,-29.01,0.25794,4,11,50.07,-30.48,0.09004,12,6.84,-29.88,0.84111,13,-37.15,-11.33,0.06885,14,-73.11,0.75,0,3,11,43.57,-7.1,0.76083,12,-6.94,-9.91,0.23917,14,-69.62,24.76,0,2,11,46.6,2.05,0.99997,13,-32.49,21.05,3.0E-5,3,11,36.45,13.25,0.98967,12,-20.32,7,0.00809,13,-39.56,34.41,0.00224,4,11,46.89,25.87,0.64052,12,-14.57,22.33,0.30039,13,-26.34,44.06,0.05227,14,-53.3,53.59,0.00682,3,11,32.58,36.08,0.64628,12,-31.42,27.31,0.30773,13,-37.68,57.48,0.04599,4,11,34.39,39.76,0.64552,12,-30.92,31.38,0.30815,13,-35.02,60.6,0.04625,14,-59.13,71.34,8.0E-5,4,11,59.63,39.97,0.34813,12,-7.13,39.83,0.43174,13,-10.51,54.59,0.16331,14,-35.95,61.37,0.05682,4,11,62.2,46.95,0.24584,12,-6.99,47.26,0.44091,13,-6.3,60.72,0.21762,14,-30.78,66.72,0.09563,4,11,76.76,56.08,0.142,12,3.8,60.64,0.40374,13,10.06,65.97,0.27809,14,-13.78,69.19,0.17617,4,11,83.49,52.11,0.10503,12,11.46,59.09,0.3642,13,15.61,60.46,0.29593,14,-9.21,62.85,0.23485,4,11,108.59,60.48,0.00722,12,32.45,75.2,0.13802,13,42,62.38,0.20959,14,17.13,60.38,0.64517,4,11,101.75,66.29,0.00374,12,24.08,78.46,0.12716,13,36.8,69.7,0.19794,14,13.21,68.46,0.67116,4,11,118.64,68.53,0.0016,12,39.32,86.09,0.10759,13,53.72,67.71,0.17374,14,29.57,63.7,0.71706,3,12,60.04,83.61,0.05509,13,69.67,54.24,0.09401,14,43.08,47.78,0.8509,3,12,76.46,80.34,0.01912,13,81.59,42.5,0.02904,14,52.89,34.23,0.95184,3,12,92.87,77.08,0.00387,13,93.51,30.75,0.0026,14,62.71,20.68,0.99353,2,12,102.33,59.1,3.0E-5,14,57.42,1.06,0.99997,2,13,89.56,-9.68,0.0092,14,52.13,-18.55,0.9908,2,13,92.72,-15.28,0.0155,14,54.33,-24.59,0.9845,2,13,97.57,-21.53,0.0141,14,58.07,-31.55,0.9859,2,13,86.03,-20.78,0.03876,14,46.82,-28.91,0.96124,2,13,86.68,-38.46,0.13586,14,44.53,-46.46,0.86414,2,13,94.8,-44.54,0.14316,14,51.55,-53.79,0.85684,2,13,93.96,-45.53,0.14323,14,50.55,-54.63,0.85677,2,13,90.05,-45.85,0.14573,14,46.64,-54.3,0.85427,2,13,55.02,-7.58,0.04152,14,18.41,-10.77,0.95848,3,12,51.23,-40.86,0.38969,13,-6.1,-44.9,0.5886,14,-48.03,-37.49,0.02171,4,11,80.87,22.37,0.07331,12,18.7,30.13,0.48172,13,5.74,32.29,0.35773,14,-23.6,36.69,0.08724,2,12,33.26,-8.57,0.57384,13,-3.36,-8.05,0.42616,4,11,111.41,36.89,0.00808,12,42.81,53.82,0.13465,13,38.91,38.83,0.27585,14,10.19,37.66,0.58142,3,12,82.13,-8.42,0.01697,13,37.55,-34.78,0.55228,14,-3.31,-34.71,0.43075,3,12,56.12,23.65,0.01042,13,33.45,6.3,0.65357,14,-0.57,6.49,0.33601,3,12,78.23,51.69,0.00631,13,67.33,17.59,0.00861,14,34.71,12.02,0.98508,3,12,60.13,-20.86,0.15304,13,12.33,-33.08,0.76549,14,-27.9,-28.87,0.08147,3,12,5.1,0.67,0.99913,13,-21.81,15.15,8.2E-4,14,-53.61,24.34,5.0E-5,2,13,65.61,-32.89,0.18327,14,24.68,-37.48,0.81673,4,11,73.52,-42.55,0.00374,12,32.95,-33.63,0.62512,13,-17.39,-28.82,0.37045,14,-56.51,-19.75,6.9E-4],"hull":34,"edges":[0,2,2,4,4,6,6,8,8,10,10,12,12,14,14,16,16,18,18,20,20,22,22,24,24,26,26,28,28,30,30,32,32,34,34,36,36,38,38,40,40,42,42,44,44,46,46,48,48,50,50,52,52,54,54,56,56,58,58,60,60,62,62,64,64,66,66,0],"width":174,"height":167}},"firecrB":{"firecrB":{"type":"mesh","uvs":[0.83015,0,0.85596,0,0.85575,0.15305,1,0.21779,1,0.23306,0.94996,0.31523,0.83971,0.48643,0.78458,0.57202,0.72945,0.65762,0.6192,0.82881,0.50894,1,0.41164,1,0.30873,0.98306,0.20582,0.96613,0.10291,0.94919,0,0.93225,0,0.9038,0.06396,0.80447,0.12792,0.70513,0.19188,0.6058,0.25584,0.50646,0.3198,0.40713,0.38375,0.3078,0.44771,0.20846,0.51167,0.10913,0.70831,0.12916,0.74923,0.1324,0.71969,0.27958,0.38117,0.81357,0.54196,0.47505,0.42218,0.66434,0.73589,0.43227,0.49136,0.82714,0.17871,0.84709,0.58252,0.23435,0.59216,0.34585,0.58728,0.53726,0.38695,0.5777,0.44341,0.4088,0.52871,0.75823,0.3051,0.73236,0.55385,0.62198,0.66525,0.53534,0.32672,0.90482,0.76754,0.37183,0.45647,0.89597,0.87894,0.22185,0.82351,0.40136],"triangles":[1,26,0,2,26,1,27,46,5,5,46,4,34,25,27,46,26,2,46,27,26,27,25,26,23,24,34,34,24,25,46,3,4,46,2,3,29,20,38,38,20,21,7,42,6,36,29,42,42,31,6,42,29,31,31,47,6,6,47,5,29,35,31,29,38,35,31,44,47,31,35,44,21,22,38,35,22,34,34,22,23,22,35,38,47,44,5,35,27,44,44,27,5,35,34,27,11,45,10,10,45,9,45,32,9,12,43,11,11,43,45,12,13,43,43,13,33,13,14,33,33,14,16,14,15,16,43,28,45,43,33,28,16,17,33,45,28,32,17,18,33,33,40,28,33,18,40,32,39,9,9,39,8,32,28,39,28,40,39,40,30,39,39,41,8,39,30,41,30,40,19,40,18,19,8,41,42,41,36,42,19,37,30,30,37,41,8,42,7,41,37,36,19,20,37,29,37,20,37,29,36],"vertices":[1,19,25.05,5.29,1,1,19,26.02,0.01,1,3,16,143.52,-20.45,0.0038,17,53.98,-18.02,0.518,18,4.77,-17.89,0.4782,3,16,131.29,-57.18,0.11046,17,43.43,-55.27,0.88245,18,-4.67,-55.43,0.00709,3,16,125.89,-59.23,0.12667,17,38.13,-57.56,0.86943,18,-9.9,-57.88,0.0039,2,16,93.16,-60.52,0.43695,17,5.49,-60.34,0.56305,3,15,147.71,-61.33,0.18562,16,24.52,-62.05,0.80177,17,-63.01,-64.97,0.01261,2,15,113.43,-63.06,0.62225,16,-9.79,-62.81,0.37775,2,15,79.15,-64.78,0.93224,16,-44.11,-63.57,0.06776,1,15,10.58,-68.24,1,1,15,-57.99,-71.69,1,1,15,-65.7,-52.98,1,1,15,-67.93,-30.75,1,1,15,-70.17,-8.52,1,1,15,-72.41,13.71,1,1,15,-74.64,35.94,1,1,15,-64.7,40.04,1,1,15,-24.92,42.05,1,1,15,14.87,44.05,1,2,15,54.65,46.06,0.99984,16,-65.48,47.92,1.6E-4,2,15,94.44,48.07,0.86889,16,-25.65,48.81,0.13111,2,15,134.22,50.07,0.25622,16,14.17,49.69,0.74378,3,15,174.01,52.08,0.00489,16,54,50.58,0.93755,17,-38.67,48.88,0.05755,2,16,93.82,51.47,0.43013,17,1.07,51.57,0.56987,2,16,133.65,52.35,0.04369,17,40.81,54.26,0.95631,2,17,50.1,13.71,0.84367,18,-0.05,13.72,0.15633,2,17,52.35,5.42,0.33952,18,2.45,5.49,0.66048,2,16,88.76,-10.96,0.5738,17,-1.15,-11.03,0.4262,1,15,-2.96,-20.27,1,2,15,128.09,-2.43,0.00985,16,6.57,-2.62,0.99015,1,15,52.45,-6.66,1,3,15,158.41,-33.57,0.05444,16,36,-34.6,0.92732,17,-52.79,-37.03,0.01823,1,15,1.03,-43.41,1,1,15,-30.72,13.84,1,2,16,94.62,21.78,0.37959,17,3.22,21.95,0.62041,1,16,55.93,4.95,1,2,15,109.94,-20.11,0.79475,16,-12.07,-19.78,0.20525,2,15,79.93,12.59,0.99864,16,-41.15,13.76,0.00136,2,15,143.44,26.06,0.0914,16,22.71,25.43,0.9086,1,15,28.07,-40.67,1,1,15,19.4,6.06,1,2,15,77.68,-25.88,0.98313,16,-44.48,-24.64,0.01687,2,15,116.79,-34.83,0.589,16,-5.64,-34.68,0.411,1,15,-39.17,-22.94,1,3,15,182.04,-30.95,0.00377,16,59.7,-32.64,0.89442,17,-29.2,-34,0.10182,1,15,-25.79,-46.61,1,3,16,120.92,-34.19,0.08924,17,32.03,-32.77,0.89015,18,-16.74,-33.28,0.02061,3,15,176.16,-45.97,0.0199,16,53.39,-47.49,0.8752,17,-34.83,-49.12,0.1049],"hull":27,"edges":[0,2,2,4,4,6,6,8,8,10,10,12,12,14,14,16,16,18,18,20,20,22,22,24,24,26,26,28,28,30,30,32,32,34,34,36,36,38,38,40,40,42,42,44,44,46,46,48,48,50,50,52,52,0],"width":208,"height":378}},"sparkB2":{"爆炸_05/001":{"x":0.5,"y":0.5,"width":121,"height":119},"爆炸_05/002":{"x":0.5,"width":131,"height":130},"爆炸_05/003":{"x":0.5,"width":173,"height":172},"爆炸_05/004":{"x":0.5,"width":205,"height":206},"爆炸_05/005":{"x":0.5,"y":0.5,"width":229,"height":233},"爆炸_05/006":{"width":240,"height":244},"爆炸_05/007":{"x":0.5,"width":237,"height":256},"爆炸_05/008":{"y":0.5,"width":250,"height":265},"爆炸_05/009":{"x":0.5,"width":259,"height":250},"爆炸_05/010":{"width":260,"height":250}},"glow":{"glow":{"x":0.5,"width":267,"height":270}},"Icon_Common_24":{"Icon_Common_24":{"width":512,"height":512}},"FireSeq":{"爆炸_紅1/1_00":{"width":384,"height":216},"爆炸_紅1/1_01":{"width":384,"height":216},"爆炸_紅1/1_02":{"width":384,"height":216},"爆炸_紅1/1_03":{"width":384,"height":216},"爆炸_紅1/1_04":{"width":384,"height":216},"爆炸_紅1/1_05":{"width":384,"height":216},"爆炸_紅1/1_06":{"width":384,"height":216},"爆炸_紅1/1_07":{"width":384,"height":216},"爆炸_紅1/1_08":{"width":384,"height":216},"爆炸_紅1/1_09":{"width":384,"height":216},"爆炸_紅1/1_10":{"width":384,"height":216},"爆炸_紅1/1_11":{"width":384,"height":216},"爆炸_紅1/1_12":{"width":384,"height":216},"爆炸_紅1/1_13":{"width":384,"height":216},"爆炸_紅1/1_14":{"width":384,"height":216},"爆炸_紅1/1_15":{"width":384,"height":216},"爆炸_紅1/1_16":{"width":384,"height":216},"爆炸_紅1/1_17":{"width":384,"height":216},"爆炸_紅1/1_18":{"width":384,"height":216},"爆炸_紅1/1_19":{"width":384,"height":216},"爆炸_紅1/1_20":{"width":384,"height":216},"爆炸_紅1/1_21":{"width":384,"height":216},"爆炸_紅1/1_22":{"width":384,"height":216},"爆炸_紅1/1_23":{"width":384,"height":216}},"MEGA_Seq":{"MEGA_Seq/Comp 1_00000":{"x":0.5,"width":325,"height":84},"MEGA_Seq/Comp 1_00001":{"x":0.5,"width":325,"height":84},"MEGA_Seq/Comp 1_00002":{"x":0.5,"width":325,"height":84},"MEGA_Seq/Comp 1_00003":{"x":0.5,"width":325,"height":84},"MEGA_Seq/Comp 1_00004":{"x":0.5,"width":325,"height":84},"MEGA_Seq/Comp 1_00005":{"x":0.5,"width":325,"height":84},"MEGA_Seq/Comp 1_00006":{"x":0.5,"width":325,"height":84},"MEGA_Seq/Comp 1_00007":{"x":0.5,"width":325,"height":84},"MEGA_Seq/Comp 1_00008":{"x":0.5,"width":325,"height":84},"MEGA_Seq/Comp 1_00009":{"x":0.5,"width":325,"height":84},"MEGA_Seq/Comp 1_00010":{"x":0.5,"width":325,"height":84},"MEGA_Seq/Comp 1_00011":{"x":0.5,"width":325,"height":84},"MEGA_Seq/Comp 1_00012":{"x":0.5,"width":325,"height":84},"MEGA_Seq/Comp 1_00013":{"x":0.5,"width":325,"height":84},"MEGA_Seq/Comp 1_00014":{"x":0.5,"width":325,"height":84},"MEGA_Seq/Comp 1_00015":{"x":0.5,"width":325,"height":84},"MEGA_Seq/Comp 1_00016":{"x":0.5,"width":325,"height":84},"MEGA_Seq/Comp 1_00017":{"x":0.5,"width":325,"height":84},"MEGA_Seq/Comp 1_00018":{"x":0.5,"width":325,"height":84},"MEGA_Seq/Comp 1_00019":{"x":0.5,"width":325,"height":84},"MEGA_Seq/Comp 1_00020":{"x":0.5,"width":325,"height":84},"MEGA_Seq/Comp 1_00021":{"x":0.5,"width":325,"height":84},"MEGA_Seq/Comp 1_00022":{"x":0.5,"width":325,"height":84},"MEGA_Seq/Comp 1_00023":{"x":0.5,"width":325,"height":84},"MEGA_Seq/Comp 1_00024":{"x":0.5,"width":325,"height":84},"MEGA_Seq/Comp 1_00025":{"x":0.5,"width":325,"height":84},"MEGA_Seq/Comp 1_00026":{"x":0.5,"width":325,"height":84},"MEGA_Seq/Comp 1_00027":{"x":0.5,"width":325,"height":84},"MEGA_Seq/Comp 1_00028":{"x":0.5,"width":325,"height":84},"MEGA_Seq/Comp 1_00029":{"x":0.5,"width":325,"height":84}},"BAO_Left":{"BAO_Left":{"x":279.32,"y":-42.08,"rotation":-18.38,"width":936,"height":200}},"RedLig":{"PZ003":{"x":9.5,"y":6,"width":1037,"height":640}},"GF01":{"GF01":{"x":-191.32,"y":0.65,"width":492,"height":344}},"GF02":{"GF02":{"x":177.21,"y":13.15,"width":513,"height":357}},"2_WIN2":{"WIN":{"x":9.5,"y":9,"width":455,"height":180}},"sparkB":{"sparkB":{"type":"mesh","uvs":[0.69346,0.00205,0.85643,0.15712,0.85843,0.0301,0.92578,0.14328,0.99312,0.25647,0.99299,0.47762,0.99287,0.69876,0.94075,0.88315,0.82064,0.95828,0.64461,0.8842,0.67215,0.9541,0.56152,0.99945,0.44461,0.90845,0.40122,0.97053,0.23986,0.99365,0.07368,0.94115,0.06406,0.87556,0.07652,0.8365,0.11074,0.82182,0.0126,0.64325,0.06631,0.52118,0.06675,0.38766,0.00251,0.40416,0.03017,0.26763,0.14638,0.33705,0.12596,0.19195,0.17735,0.02934,0.30934,0.0293,0.44134,0.02926,0.44238,0.06788,0.77607,0.4776,0.23998,0.7793,0.40866,0.59706,0.55251,0.27297,0.76355,0.74999,0.29255,0.38858,0.77432,0.23325,0.28943,0.21463,0.57282,0.43909,0.18855,0.62521,0.63424,0.6668,0.83166,0.61384],"triangles":[1,2,3,37,26,27,25,26,37,27,28,29,37,27,29,36,0,1,33,29,0,33,0,36,37,29,33,24,25,37,21,23,24,35,37,33,24,37,35,22,23,21,38,33,36,35,33,38,4,30,36,38,36,30,1,3,4,4,36,1,5,30,4,32,35,38,24,20,21,24,35,20,41,30,5,39,35,32,39,20,35,40,38,30,40,30,41,32,38,40,6,41,5,34,40,41,34,41,6,31,39,32,7,34,6,9,40,34,12,32,40,34,8,9,7,8,34,19,20,39,18,19,39,18,39,31,12,40,9,31,32,12,11,12,9,11,9,10,18,15,16,13,31,12,14,18,31,14,31,13,18,16,17,14,15,18],"vertices":[2,19,96.88,-10.95,0.00118,20,66.35,-9.64,0.99882,2,19,80.12,-36.39,0.09498,20,50.08,-35.42,0.90502,2,19,97.16,-33.54,0.08941,20,67.06,-32.23,0.91059,2,19,83.66,-45.26,0.11287,20,53.8,-44.21,0.88713,3,18,114.33,-37.35,4.0E-5,19,70.16,-56.98,0.20059,20,40.54,-56.2,0.79938,3,18,87.08,-50.08,0.02764,19,40.58,-62.4,0.47894,20,11.06,-62.2,0.49342,3,18,59.83,-62.82,0.16244,19,10.99,-67.82,0.67293,20,-18.41,-68.19,0.16462,3,18,34.14,-67.08,0.31028,19,-14.94,-65.43,0.64976,20,-44.38,-66.31,0.03996,3,18,18.01,-56.72,0.39508,19,-27.92,-51.32,0.59275,20,-57.64,-52.47,0.01217,3,18,17.06,-30.93,0.75273,19,-22.3,-26.13,0.24617,20,-52.52,-27.17,0.0011,2,18,10.03,-38.33,0.90238,19,-30.98,-31.51,0.09762,2,18,-1.89,-27.42,0.96463,19,-39.75,-17.93,0.03537,3,17,52.14,-7.95,0.15928,18,2.63,-7.87,0.84026,19,-30.43,-0.17,4.5E-4,2,17,42.06,-5.92,0.99168,18,-7.5,-6.15,0.00832,3,17,30.53,12.82,0.95708,18,-19.58,12.25,0.04162,19,-46.82,24.92,0.0013,3,17,28.18,36.25,0.80676,18,-22.63,35.59,0.17178,19,-43.85,48.28,0.02145,4,17,35.85,40.98,0.7495,18,-15.1,40.55,0.214,19,-35.31,51.16,0.03543,20,-67.04,49.86,0.00107,4,17,41.4,41.54,0.6978,18,-9.58,41.28,0.24962,19,-29.78,50.47,0.04967,20,-61.5,49.27,0.00291,4,17,45.06,38.1,0.59765,18,-5.81,37.94,0.31445,19,-26.98,46.29,0.08005,20,-58.62,45.14,0.00785,4,17,62.09,59.9,0.19505,18,10.57,60.24,0.42138,19,-5.49,63.71,0.29616,20,-37.47,62.98,0.08741,4,17,80.21,59.83,0.091,18,28.68,60.71,0.32447,19,12.15,59.57,0.37134,20,-19.76,59.2,0.21319,4,17,96.9,66.98,0.01736,18,45.15,68.35,0.18536,19,30.02,62.8,0.36906,20,-1.95,62.77,0.42822,4,17,91.4,74.05,0.01134,18,39.44,75.26,0.17781,19,26.25,70.92,0.37213,20,-5.89,70.82,0.43873,4,17,109.92,78,0.00853,18,57.84,79.74,0.17109,19,45.18,70.6,0.36923,20,13.05,70.87,0.45115,4,17,107.49,59.85,0.01032,18,55.94,61.53,0.134,19,38.73,53.47,0.30886,20,6.94,53.61,0.54682,4,17,124.5,70.21,1.8E-4,18,72.65,72.4,0.03268,19,57.64,59.74,0.12097,20,25.72,60.26,0.84616,3,18,95.62,75.49,0.00643,19,80.65,56.91,0.04817,20,48.78,57.88,0.9454,3,18,103.18,59.35,0.00205,19,83.87,39.39,0.02531,20,52.35,40.43,0.97264,2,19,87.1,21.86,0.00535,20,55.92,22.97,0.99465,3,18,106.04,40.86,4.0E-5,19,81.96,20.78,0.00412,20,50.8,21.78,0.99583,3,18,74.67,-23.56,0.01451,19,35.29,-33.6,0.49102,20,5.21,-33.5,0.49447,4,17,57.29,24.38,0.34239,18,6.82,24.59,0.54662,19,-18.14,30.17,0.1031,20,-49.46,29.2,0.00788,4,17,89.08,13.31,0.0057,18,38.93,14.47,0.17827,19,10.35,12.25,0.79598,20,-20.63,11.85,0.02005,2,18,87.08,15.57,5.0E-5,20,26.44,1.63,0.99995,3,18,40.4,-37.73,0.30302,19,-1.45,-38.63,0.6409,20,-31.42,-39.25,0.05608,4,17,108.89,38.95,0.00629,18,57.96,40.69,0.09413,19,35.4,32.79,0.33539,20,4.02,32.88,0.56419,2,19,67.93,-27.36,0.08934,20,37.72,-26.62,0.91066,4,17,130.43,48.73,6.0E-5,18,79.21,51.1,0.02298,19,58.6,37.48,0.09693,20,27.11,38.02,0.88004,2,19,35.48,-5.66,0.20228,20,4.85,-5.57,0.79772,4,17,73.77,39.07,0.13778,18,22.86,39.76,0.43011,19,1.22,40.79,0.34009,20,-30.32,40.2,0.09202,3,18,43.25,-17.13,0.17512,19,6.52,-19.41,0.78437,20,-23.83,-19.89,0.04051,3,18,61.07,-38.21,0.10246,19,18.42,-44.33,0.66526,20,-11.44,-44.56,0.23228],"hull":30,"edges":[0,2,2,4,4,6,6,8,8,10,10,12,12,14,14,16,16,18,18,20,20,22,22,24,24,26,26,28,28,30,30,32,32,34,34,36,36,38,38,40,40,42,42,44,44,46,46,48,48,50,50,52,52,54,54,56,56,58,58,0],"width":135,"height":136}},"2_WIN":{"WIN":{"x":9.5,"y":9,"width":455,"height":180}},"Jew02":{"Jew02":{"x":-4,"y":127,"width":410,"height":338}},"BAO_Right":{"BAO_Right":{"x":-293.78,"y":-4.38,"rotation":11.53,"width":936,"height":200}},"sparkA2":{"sparkA":{"type":"mesh","uvs":[0.65205,0.07424,0.7316,0.15714,0.75557,0.24847,0.84073,0.29714,0.86302,0.30359,0.9489,0.46105,0.94349,0.57993,0.87144,0.65505,0.79939,0.73017,0.69533,0.82685,0.64045,0.83478,0.60843,0.91891,0.5169,0.89616,0.5005,1,0.47696,1,0.41182,0.86496,0.36931,0.86961,0.28534,0.81547,0.2887,0.76881,0.1819,0.65605,0.16928,0.70819,0.11489,0.62333,0.11428,0.49834,0.12118,0.39839,0.12809,0.29844,0.22387,0.22889,0.31964,0.15934,0.33231,0.12316,0.34155,0.07682,0.3813,0.1323,0.45623,0.06062,0.45247,0,0.45997,0,0.47596,0.01657,0.43926,0.32484,0.83039,0.45826,0.44873,0.70429,0.65904,0.589,0.29641,0.5786,0.62333,0.29874,0.45901,0.47709,0.28331,0.36657,0.70994,0.42025,0.62642,0.76319,0.51043,0.17823,0.80218,0.57223],"triangles":[18,19,38,20,21,19,38,19,22,19,21,22,38,22,41,22,23,41,38,41,40,41,34,40,40,34,39,23,24,41,41,26,34,26,29,34,26,27,29,24,25,41,41,25,26,34,44,39,34,29,44,39,0,1,39,44,0,29,30,44,44,30,0,0,30,33,27,28,29,33,31,32,33,30,31,36,40,37,36,38,40,37,42,45,37,40,42,6,35,5,45,42,35,40,39,42,35,4,5,35,3,4,35,42,3,42,2,3,42,39,2,39,1,2,15,16,18,16,17,18,43,12,36,12,15,36,15,18,36,9,43,8,18,38,36,43,37,8,43,36,37,8,45,7,8,37,45,7,45,6,45,35,6,13,14,12,14,15,12,11,12,10,10,12,43,10,43,9],"vertices":[3,12,118.71,-18.03,8.8E-4,13,62.83,-62.91,0.32632,14,16.98,-66.63,0.67281,3,12,103.26,-30.05,0.01584,13,43.32,-64.46,0.4711,14,-2.52,-64.93,0.51305,3,12,87.61,-32.29,0.07525,13,29.01,-57.73,0.61987,14,-15.53,-55.94,0.30488,3,12,77.7,-45.99,0.20925,13,13.21,-63.73,0.68396,14,-32.1,-59.24,0.10679,3,12,76.15,-49.7,0.23052,13,9.87,-65.98,0.67991,14,-35.76,-60.91,0.08957,3,12,48.21,-61.27,0.46368,13,-19.83,-60.29,0.52848,14,-64.12,-50.39,0.00783,4,11,61.52,-64.05,5.4E-4,12,28.62,-57.87,0.59654,13,-34.33,-46.69,0.4029,14,-76.17,-34.58,2.0E-5,3,11,55.79,-47.26,0.01327,12,17.73,-43.88,0.72879,13,-35.74,-29.01,0.25794,4,11,50.07,-30.48,0.09004,12,6.84,-29.88,0.84111,13,-37.15,-11.33,0.06885,14,-73.11,0.75,0,3,11,43.57,-7.1,0.76083,12,-6.94,-9.91,0.23917,14,-69.62,24.76,0,2,11,46.6,2.05,0.99997,13,-32.49,21.05,3.0E-5,3,11,36.45,13.25,0.98967,12,-20.32,7,0.00809,13,-39.56,34.41,0.00224,4,11,46.89,25.87,0.64052,12,-14.57,22.33,0.30039,13,-26.34,44.06,0.05227,14,-53.3,53.59,0.00682,3,11,32.58,36.08,0.64628,12,-31.42,27.31,0.30773,13,-37.68,57.48,0.04599,4,11,34.39,39.76,0.64552,12,-30.92,31.38,0.30815,13,-35.02,60.6,0.04625,14,-59.13,71.34,8.0E-5,4,11,59.63,39.97,0.34813,12,-7.13,39.83,0.43174,13,-10.51,54.59,0.16331,14,-35.95,61.37,0.05682,4,11,62.2,46.95,0.24584,12,-6.99,47.26,0.44091,13,-6.3,60.72,0.21762,14,-30.78,66.72,0.09563,4,11,76.76,56.08,0.142,12,3.8,60.64,0.40374,13,10.06,65.97,0.27809,14,-13.78,69.19,0.17617,4,11,83.49,52.11,0.10503,12,11.46,59.09,0.3642,13,15.61,60.46,0.29593,14,-9.21,62.85,0.23485,4,11,108.59,60.48,0.00722,12,32.45,75.2,0.13802,13,42,62.38,0.20959,14,17.13,60.38,0.64517,4,11,101.75,66.29,0.00374,12,24.08,78.46,0.12716,13,36.8,69.7,0.19794,14,13.21,68.46,0.67116,4,11,118.64,68.53,0.0016,12,39.32,86.09,0.10759,13,53.72,67.71,0.17374,14,29.57,63.7,0.71706,3,12,60.04,83.61,0.05509,13,69.67,54.24,0.09401,14,43.08,47.78,0.8509,3,12,76.46,80.34,0.01912,13,81.59,42.5,0.02904,14,52.89,34.23,0.95184,3,12,92.87,77.08,0.00387,13,93.51,30.75,0.0026,14,62.71,20.68,0.99353,2,12,102.33,59.1,3.0E-5,14,57.42,1.06,0.99997,2,13,89.56,-9.68,0.0092,14,52.13,-18.55,0.9908,2,13,92.72,-15.28,0.0155,14,54.33,-24.59,0.9845,2,13,97.57,-21.53,0.0141,14,58.07,-31.55,0.9859,2,13,86.03,-20.78,0.03876,14,46.82,-28.91,0.96124,2,13,86.68,-38.46,0.13586,14,44.53,-46.46,0.86414,2,13,94.8,-44.54,0.14316,14,51.55,-53.79,0.85684,2,13,93.96,-45.53,0.14323,14,50.55,-54.63,0.85677,2,13,90.05,-45.85,0.14573,14,46.64,-54.3,0.85427,2,13,55.02,-7.58,0.04152,14,18.41,-10.77,0.95848,3,12,51.23,-40.86,0.38969,13,-6.1,-44.9,0.5886,14,-48.03,-37.49,0.02171,4,11,80.87,22.37,0.07331,12,18.7,30.13,0.48172,13,5.74,32.29,0.35773,14,-23.6,36.69,0.08724,2,12,33.26,-8.57,0.57384,13,-3.36,-8.05,0.42616,4,11,111.41,36.89,0.00808,12,42.81,53.82,0.13465,13,38.91,38.83,0.27585,14,10.19,37.66,0.58142,3,12,82.13,-8.42,0.01697,13,37.55,-34.78,0.55228,14,-3.31,-34.71,0.43075,3,12,56.12,23.65,0.01042,13,33.45,6.3,0.65357,14,-0.57,6.49,0.33601,3,12,78.23,51.69,0.00631,13,67.33,17.59,0.00861,14,34.71,12.02,0.98508,3,12,60.13,-20.86,0.15304,13,12.33,-33.08,0.76549,14,-27.9,-28.87,0.08147,3,12,5.1,0.67,0.99913,13,-21.81,15.15,8.2E-4,14,-53.61,24.34,5.0E-5,2,13,65.61,-32.89,0.18327,14,24.68,-37.48,0.81673,4,11,73.52,-42.55,0.00374,12,32.95,-33.63,0.62512,13,-17.39,-28.82,0.37045,14,-56.51,-19.75,6.9E-4],"hull":34,"edges":[0,2,2,4,4,6,6,8,8,10,10,12,12,14,14,16,16,18,18,20,20,22,22,24,24,26,26,28,28,30,30,32,32,34,34,36,36,38,38,40,40,42,42,44,44,46,46,48,48,50,50,52,52,54,54,56,56,58,58,60,60,62,62,64,64,66,66,0],"width":174,"height":167}},"sparkA3":{"爆炸_05/001":{"x":0.5,"y":0.5,"width":121,"height":119},"爆炸_05/002":{"x":0.5,"width":131,"height":130},"爆炸_05/003":{"x":0.5,"width":173,"height":172},"爆炸_05/004":{"x":0.5,"width":205,"height":206},"爆炸_05/005":{"x":0.5,"y":0.5,"width":229,"height":233},"爆炸_05/006":{"width":240,"height":244},"爆炸_05/007":{"x":0.5,"width":237,"height":256},"爆炸_05/008":{"y":0.5,"width":250,"height":265},"爆炸_05/009":{"x":0.5,"width":259,"height":250},"爆炸_05/010":{"width":260,"height":250}},"1_MEGA2":{"MEGA":{"x":1.5,"y":-19.74,"width":649,"height":168}},"RedLig2":{"PZ004":{"x":5.5,"width":875,"height":652}},"RedLig3":{"PZ001":{"width":456,"height":264}},"RedLig4":{"PZ002":{"x":0.5,"y":0.5,"width":589,"height":341}},"firecrA":{"firecrA":{"type":"mesh","uvs":[0.09736,0,0.27695,0.05743,0.45653,0.11486,0.52447,0.20819,0.5924,0.30152,0.72827,0.48818,0.86413,0.67485,1,0.86151,1,0.88365,0.85926,0.93606,0.74784,0.96803,0.63642,1,0.56378,1,0.49345,0.903,0.42311,0.80599,0.35277,0.70899,0.28243,0.61199,0.2121,0.51499,0.14176,0.41798,0.07142,0.32098,0.00108,0.22398,0.04526,0.11199,0.08944,0,0.64967,0.76566,0.30437,0.35336,0.48277,0.46583,0.80927,0.76276,0.24144,0.24054,0.44343,0.33263,0.49661,0.65129,0.17731,0.11588,0.64441,0.6088,0.34152,0.50009,0.65701,0.87845,0.36927,0.24311,0.14784,0.21231,0.56172,0.39704,0.2785,0.16395,0.66398,0.69822,0.4281,0.2312,0.79501,0.84092,0.51762,0.72602,0.69335,0.60007,0.56436,0.5302],"triangles":[0,21,22,35,21,30,0,30,21,30,1,37,30,0,1,19,27,24,19,20,35,19,35,27,35,20,21,39,34,37,34,27,37,27,35,37,39,2,3,39,37,2,35,30,37,37,1,2,17,18,32,18,24,32,32,24,25,43,25,36,36,4,5,24,28,25,25,28,36,18,19,24,36,28,4,24,34,28,24,27,34,34,39,28,4,39,3,4,28,39,10,11,33,11,12,33,12,13,33,9,10,40,10,33,40,8,9,7,33,14,23,23,14,41,14,33,13,9,40,7,33,23,40,40,26,7,26,6,7,40,23,26,14,15,41,23,38,26,23,41,38,26,38,6,15,29,41,41,29,38,15,16,29,29,31,38,38,42,6,38,31,42,42,5,6,16,32,29,29,32,43,29,43,31,43,32,25,16,17,32,31,43,42,42,43,5,5,43,36],"vertices":[1,13,26.32,-0.01,1,3,11,71.56,-31.38,0.1783,12,27.45,-23.72,0.78354,13,-16.54,-17.51,0.03816,3,10,128.61,-55.66,0.09296,11,34.35,-58.91,0.67017,12,1.27,-61.89,0.23687,3,10,90.79,-57.71,0.50495,11,-3.51,-57.63,0.44682,12,-34.93,-73.04,0.04823,4,9,156.72,-59.17,0.02585,10,52.97,-59.76,0.89969,11,-41.36,-56.35,0.07332,12,-71.12,-84.19,0.00113,2,9,81.13,-64.12,0.78505,10,-22.67,-63.87,0.21495,1,9,5.55,-69.07,1,1,9,-70.04,-74.02,1,1,9,-77.71,-71.15,1,1,9,-84.59,-34.17,1,1,9,-86.73,-6.12,1,1,9,-88.87,21.92,1,1,9,-83.05,37.5,1,1,9,-43.79,40.01,1,1,9,-4.53,42.53,1,1,9,34.73,45.04,1,2,9,73.99,47.56,0.89089,10,-28.56,47.88,0.10911,3,9,113.25,50.07,0.29702,10,10.72,49.95,0.70286,11,-73.8,56.66,1.2E-4,3,9,152.51,52.58,0.00931,10,50.01,52.03,0.91084,11,-34.49,55.27,0.07986,3,10,89.29,54.1,0.46242,11,4.83,53.89,0.53668,12,-63.47,35.08,9.0E-4,3,10,128.58,56.18,0.07446,11,44.15,52.5,0.8217,12,-25.86,46.61,0.10384,3,11,76.86,25.14,0.22359,12,14,31.43,0.64731,13,2.54,35.96,0.12909,1,13,27.5,1.37,1,1,9,-8.72,-11.3,1,2,10,58.88,8.67,0.99064,11,-29.46,11.3,0.00936,2,9,108.57,-14.36,0.27343,10,5.33,-14.42,0.72657,1,9,-20.52,-45.91,1,2,10,103.01,7.05,0.0454,11,14.36,5.81,0.9546,4,9,157.89,-23.18,0.0023,10,54.54,-23.79,0.97437,11,-36.63,-20.65,0.02322,12,-78.31,-48.92,1.0E-4,1,9,43.19,6.71,1,2,12,8.82,1.61,0.99842,13,-18.18,13.88,0.00158,2,9,46.06,-30.5,0.99473,10,-57.36,-29.86,0.00527,2,9,108.03,20.38,0.34033,10,5.17,20.32,0.65967,1,9,-48.4,1.75,1,3,10,91.56,-19.9,0.47227,11,0.58,-20.03,0.51113,12,-43.34,-36.17,0.0166,3,10,120.48,23.28,0.04635,11,33.19,20.44,0.92545,12,-25.75,12.73,0.0282,3,9,126.08,-40.21,0.16933,10,22.54,-40.46,0.82933,11,-69.97,-34.45,0.00134,3,10,126.37,-11.08,0.00305,11,36.04,-14.31,0.86795,12,-11.7,-19.18,0.12899,1,9,13.5,-23.11,1,3,10,90.81,-34.06,0.49626,11,-1.41,-34.07,0.46906,12,-40.64,-50.09,0.03469,1,9,-46.46,-32.72,1,1,9,15.61,11.89,1,2,9,45.16,-42.13,0.98828,10,-58.4,-41.48,0.01172,2,9,79.72,-23.52,0.91684,10,-23.63,-23.25,0.08316],"hull":23,"edges":[0,2,2,4,4,6,6,8,8,10,10,12,12,14,14,16,16,18,18,20,20,22,22,24,24,26,26,28,28,30,30,32,32,34,34,36,36,38,38,40,40,42,42,44,44,0],"width":229,"height":370}},"Jew01":{"Jew01":{"y":-33.5,"width":522,"height":335}},"fangshe02":{"fangshe02":{"width":200,"height":200}},"Jew03":{"Jew03":{"x":0.5,"y":-48.5,"width":641,"height":463}}}}],"animations":{"idle":{"slots":{"1_MEGA":{"attachment":[{"name":"MEGA"}]},"2_WIN":{"attachment":[{"name":"WIN"}]},"sparkA2":{"attachment":[{"name":"sparkA"}]},"Jew01":{"attachment":[{"name":"Jew01"}]},"GF01":{"color":[{"color":"ffffff00"}],"attachment":[{"name":"GF01"}]},"sparkB":{"attachment":[{"name":"sparkB"}]},"SMZ02":{"attachment":[{"name":"SMZ02"}]},"SMZ01":{"attachment":[{"name":"SMZ01"}]},"GF02":{"color":[{"color":"ffffff00"}],"attachment":[{"name":"GF02"}]},"firecrA":{"attachment":[{"name":"firecrA"}]},"Jew02":{"attachment":[{"name":"Jew02"}]},"Jew03":{"attachment":[{"name":"Jew03"}]},"sparkA":{"attachment":[{"name":"sparkA"}]},"firecrB":{"attachment":[{"name":"firecrB"}]},"BAO_Left":{"attachment":[{"name":"BAO_Left"}]},"BAO_Right":{"attachment":[{"name":"BAO_Right"}]}}},"in":{"slots":{"1_MEGA":{"attachment":[{"name":"MEGA"}]},"RedLig":{"color":[{"color":"ffffff00","curve":0,"c2":0.3,"c3":0.75},{"time":0.3333,"color":"ffffff91","curve":0.25,"c3":0.75},{"time":1.1,"color":"ffffff00"}],"attachment":[{"name":"PZ003"}]},"2_WIN":{"attachment":[{"name":"WIN"}]},"RedLig2":{"color":[{"color":"ffffff00","curve":0,"c2":0.3,"c3":0.75},{"time":0.3333,"color":"ffffff91","curve":0.25,"c3":0.75},{"time":1.1,"color":"ffffff00"}],"attachment":[{"name":"PZ004"}]},"sparkA2":{"attachment":[{"name":"sparkA"}]},"RedLig4":{"color":[{"color":"ffffff00","curve":0,"c2":0.3,"c3":0.75},{"time":0.3333,"color":"ffffff91","curve":0.25,"c3":0.75},{"time":1.1,"color":"ffffff00"}],"attachment":[{"name":"PZ002"}]},"fangshe02":{"color":[{"color":"ffffff00","curve":0,"c2":0.3,"c3":0.75},{"time":0.2,"color":"ffffff40","curve":0.25,"c3":0.75},{"time":0.6,"color":"ffffff00"}],"attachment":[{"name":"fangshe02"}]},"Jew01":{"attachment":[{"name":"Jew01"}]},"GF01":{"color":[{"color":"ffffff00","curve":0,"c2":0.3,"c3":0.75},{"time":0.3333,"color":"ffffffff","curve":0.25,"c3":0.75},{"time":1.1,"color":"ffffff00"}],"attachment":[{"name":"GF01"}]},"sparkB":{"attachment":[{"name":"sparkB"}]},"SMZ02":{"attachment":[{"name":"SMZ02"}]},"SMZ01":{"attachment":[{"name":"SMZ01"}]},"GF02":{"color":[{"color":"ffffff00","curve":0,"c2":0.3,"c3":0.75},{"time":0.3333,"color":"ffffffff","curve":0.25,"c3":0.75},{"time":1.1,"color":"ffffff00"}],"attachment":[{"name":"GF02"}]},"firecrA":{"attachment":[{"name":"firecrA"}]},"FireSeq":{"color":[{"color":"ffffff8b"}],"attachment":[{"name":"爆炸_紅1/1_00"},{"time":0.0333,"name":"爆炸_紅1/1_01"},{"time":0.0667,"name":"爆炸_紅1/1_02"},{"time":0.1,"name":"爆炸_紅1/1_03"},{"time":0.1333,"name":"爆炸_紅1/1_04"},{"time":0.1667,"name":"爆炸_紅1/1_05"},{"time":0.2,"name":"爆炸_紅1/1_06"},{"time":0.2333,"name":"爆炸_紅1/1_07"},{"time":0.2667,"name":"爆炸_紅1/1_08"},{"time":0.3,"name":"爆炸_紅1/1_09"},{"time":0.3333,"name":"爆炸_紅1/1_10"},{"time":0.3667,"name":"爆炸_紅1/1_11"},{"time":0.4,"name":"爆炸_紅1/1_12"},{"time":0.4333,"name":"爆炸_紅1/1_13"},{"time":0.4667,"name":"爆炸_紅1/1_14"},{"time":0.5,"name":"爆炸_紅1/1_15"},{"time":0.5333,"name":"爆炸_紅1/1_16"},{"time":0.5667,"name":"爆炸_紅1/1_17"},{"time":0.6,"name":"爆炸_紅1/1_18"},{"time":0.6333,"name":"爆炸_紅1/1_19"},{"time":0.6667,"name":"爆炸_紅1/1_20"},{"time":0.7,"name":"爆炸_紅1/1_21"},{"time":0.7333,"name":"爆炸_紅1/1_22"},{"time":0.7667,"name":"爆炸_紅1/1_23"}]},"Jew02":{"attachment":[{"name":"Jew02"}]},"Jew03":{"attachment":[{"name":"Jew03"}]},"RedLig3":{"color":[{"color":"ffffff00","curve":0,"c2":0.3,"c3":0.75},{"time":0.3333,"color":"ffffff91","curve":0.25,"c3":0.75},{"time":1.1,"color":"ffffff00"}],"attachment":[{"name":"PZ001"}]},"firecrB":{"attachment":[{"name":"firecrB"}]},"BAO_Left":{"attachment":[{"name":"BAO_Left"}]},"sparkA":{"attachment":[{"name":"sparkA"}]},"Icon_Common_24":{"color":[{"color":"ffffff00","curve":0.25,"c3":0.75},{"time":0.2,"color":"ffffff98","curve":0.25,"c3":0.75},{"time":0.6,"color":"ffffff00"}],"attachment":[{"name":"Icon_Common_24"}]},"BAO_Right":{"attachment":[{"name":"BAO_Right"}]}},"bones":{"All":{"scale":[{"x":0,"y":0,"curve":0,"c2":0.3,"c3":0.75},{"time":0.3333,"x":1.2,"y":1.2,"curve":0.25,"c3":0.75},{"time":0.5,"x":0.95,"y":0.95,"curve":0.25,"c3":0.75},{"time":0.8333}]},"FireSeq":{"scale":[{"x":7.611,"y":7.611}]},"Icon_Common_24":{"scale":[{"curve":0,"c2":0.29,"c3":0.75},{"time":0.6,"x":2.844,"y":2.844}]},"fangshe02":{"scale":[{"curve":0,"c2":0.29,"c3":0.75},{"time":0.6,"x":7.301,"y":7.301}]},"RedLig":{"scale":[{"curve":0,"c2":0.3,"c3":0.75},{"time":1.1,"x":1.548,"y":1.548}]},"RedLig2":{"scale":[{"curve":0,"c2":0.3,"c3":0.75},{"time":1.1,"x":1.729,"y":1.729}]},"RedLig3":{"scale":[{"curve":0,"c2":0.3,"c3":0.75},{"time":1.1,"x":1.641,"y":1.641}]},"RedLig4":{"scale":[{"curve":0,"c2":0.3,"c3":0.75},{"time":1.1,"x":1.641,"y":1.641}]}}},"loop":{"slots":{"RedLig":{"color":[{"color":"ffffff00"},{"time":1,"color":"ffffff63"},{"time":2,"color":"ffffff00"}],"attachment":[{"name":"PZ003"}]},"1_MEGA":{"attachment":[{"name":"MEGA"}]},"1_MEGA2":{"color":[{"color":"ffffff00","curve":0,"c2":0.29,"c3":0.75},{"time":0.6667,"color":"ffffff66","curve":0.25,"c3":0.75},{"time":1.3333,"color":"ffffff00"}],"attachment":[{"name":"MEGA"}]},"2_WIN":{"attachment":[{"name":"WIN"}]},"sparkA3":{"attachment":[{"name":"爆炸_05/001"},{"time":0.0333,"name":"爆炸_05/002"},{"time":0.0667,"name":"爆炸_05/003"},{"time":0.1,"name":"爆炸_05/004"},{"time":0.1333,"name":"爆炸_05/005"},{"time":0.1667,"name":"爆炸_05/006"},{"time":0.2,"name":"爆炸_05/007"},{"time":0.2333,"name":"爆炸_05/008"},{"time":0.2667,"name":"爆炸_05/009"},{"time":0.3,"name":"爆炸_05/010"},{"time":0.3333,"name":"爆炸_05/001"},{"time":0.3667,"name":"爆炸_05/002"},{"time":0.4,"name":"爆炸_05/003"},{"time":0.4333,"name":"爆炸_05/004"},{"time":0.4667,"name":"爆炸_05/005"},{"time":0.5,"name":"爆炸_05/006"},{"time":0.5333,"name":"爆炸_05/007"},{"time":0.5667,"name":"爆炸_05/008"},{"time":0.6,"name":"爆炸_05/009"},{"time":0.6333,"name":"爆炸_05/010"},{"time":0.6667,"name":"爆炸_05/001"},{"time":0.7,"name":"爆炸_05/002"},{"time":0.7333,"name":"爆炸_05/003"},{"time":0.7667,"name":"爆炸_05/004"},{"time":0.8,"name":"爆炸_05/005"},{"time":0.8333,"name":"爆炸_05/006"},{"time":0.8667,"name":"爆炸_05/007"},{"time":0.9,"name":"爆炸_05/008"},{"time":0.9333,"name":"爆炸_05/009"},{"time":0.9667,"name":"爆炸_05/010"},{"time":1,"name":"爆炸_05/001"},{"time":1.0333,"name":"爆炸_05/002"},{"time":1.0667,"name":"爆炸_05/003"},{"time":1.1,"name":"爆炸_05/004"},{"time":1.1333,"name":"爆炸_05/005"},{"time":1.1667,"name":"爆炸_05/006"},{"time":1.2,"name":"爆炸_05/007"},{"time":1.2333,"name":"爆炸_05/008"},{"time":1.2667,"name":"爆炸_05/009"},{"time":1.3,"name":"爆炸_05/010"},{"time":1.3333,"name":"爆炸_05/001"},{"time":1.3667,"name":"爆炸_05/002"},{"time":1.4,"name":"爆炸_05/003"},{"time":1.4333,"name":"爆炸_05/004"},{"time":1.4667,"name":"爆炸_05/005"},{"time":1.5,"name":"爆炸_05/006"},{"time":1.5333,"name":"爆炸_05/007"},{"time":1.5667,"name":"爆炸_05/008"},{"time":1.6,"name":"爆炸_05/009"},{"time":1.6333,"name":"爆炸_05/010"}]},"RedLig2":{"color":[{"color":"ffffff00"},{"time":1,"color":"ffffff59"},{"time":2,"color":"ffffff00"}],"attachment":[{"name":"PZ004"}]},"MEGA_Seq":{"attachment":[{"time":0.2333,"name":"MEGA_Seq/Comp 1_00000"},{"time":0.2667,"name":"MEGA_Seq/Comp 1_00001"},{"time":0.3,"name":"MEGA_Seq/Comp 1_00002"},{"time":0.3333,"name":"MEGA_Seq/Comp 1_00003"},{"time":0.3667,"name":"MEGA_Seq/Comp 1_00004"},{"time":0.4,"name":"MEGA_Seq/Comp 1_00005"},{"time":0.4333,"name":"MEGA_Seq/Comp 1_00006"},{"time":0.4667,"name":"MEGA_Seq/Comp 1_00007"},{"time":0.5,"name":"MEGA_Seq/Comp 1_00008"},{"time":0.5333,"name":"MEGA_Seq/Comp 1_00009"},{"time":0.5667,"name":"MEGA_Seq/Comp 1_00010"},{"time":0.6,"name":"MEGA_Seq/Comp 1_00011"},{"time":0.6333,"name":"MEGA_Seq/Comp 1_00012"},{"time":0.6667,"name":"MEGA_Seq/Comp 1_00013"},{"time":0.7,"name":"MEGA_Seq/Comp 1_00014"},{"time":0.7333,"name":"MEGA_Seq/Comp 1_00015"},{"time":0.7667,"name":"MEGA_Seq/Comp 1_00016"},{"time":0.8,"name":"MEGA_Seq/Comp 1_00017"},{"time":0.8333,"name":"MEGA_Seq/Comp 1_00018"},{"time":0.8667,"name":"MEGA_Seq/Comp 1_00019"},{"time":0.9,"name":"MEGA_Seq/Comp 1_00020"},{"time":0.9333,"name":"MEGA_Seq/Comp 1_00021"},{"time":0.9667,"name":"MEGA_Seq/Comp 1_00022"},{"time":1,"name":"MEGA_Seq/Comp 1_00023"},{"time":1.0333,"name":"MEGA_Seq/Comp 1_00024"},{"time":1.0667,"name":"MEGA_Seq/Comp 1_00025"},{"time":1.1,"name":"MEGA_Seq/Comp 1_00026"},{"time":1.1333,"name":"MEGA_Seq/Comp 1_00027"},{"time":1.1667,"name":"MEGA_Seq/Comp 1_00028"},{"time":1.2,"name":"MEGA_Seq/Comp 1_00029"},{"time":1.2333,"name":null}]},"RedLig4":{"color":[{"color":"ffffff00"},{"time":0.5,"color":"ffffff6e"},{"time":1,"color":"ffffff00"}],"attachment":[{"name":"PZ002"}]},"Jew01":{"attachment":[{"name":"Jew01"}]},"GF01":{"color":[{"color":"ffffff00","curve":0,"c2":0.3,"c3":0.75},{"time":0.5,"color":"ffffffff","curve":0.25,"c3":0.75},{"time":1,"color":"ffffff00"}],"attachment":[{"name":"GF01"}]},"sparkB2":{"attachment":[{"name":"爆炸_05/001"},{"time":0.0333,"name":"爆炸_05/002"},{"time":0.0667,"name":"爆炸_05/003"},{"time":0.1,"name":"爆炸_05/004"},{"time":0.1333,"name":"爆炸_05/005"},{"time":0.1667,"name":"爆炸_05/006"},{"time":0.2,"name":"爆炸_05/007"},{"time":0.2333,"name":"爆炸_05/008"},{"time":0.2667,"name":"爆炸_05/009"},{"time":0.3,"name":"爆炸_05/010"},{"time":0.3333,"name":"爆炸_05/001"},{"time":0.3667,"name":"爆炸_05/002"},{"time":0.4,"name":"爆炸_05/003"},{"time":0.4333,"name":"爆炸_05/004"},{"time":0.4667,"name":"爆炸_05/005"},{"time":0.5,"name":"爆炸_05/006"},{"time":0.5333,"name":"爆炸_05/007"},{"time":0.5667,"name":"爆炸_05/008"},{"time":0.6,"name":"爆炸_05/009"},{"time":0.6333,"name":"爆炸_05/010"},{"time":0.6667,"name":"爆炸_05/001"},{"time":0.7,"name":"爆炸_05/002"},{"time":0.7333,"name":"爆炸_05/003"},{"time":0.7667,"name":"爆炸_05/004"},{"time":0.8,"name":"爆炸_05/005"},{"time":0.8333,"name":"爆炸_05/006"},{"time":0.8667,"name":"爆炸_05/007"},{"time":0.9,"name":"爆炸_05/008"},{"time":0.9333,"name":"爆炸_05/009"},{"time":0.9667,"name":"爆炸_05/010"},{"time":1,"name":"爆炸_05/001"},{"time":1.0333,"name":"爆炸_05/002"},{"time":1.0667,"name":"爆炸_05/003"},{"time":1.1,"name":"爆炸_05/004"},{"time":1.1333,"name":"爆炸_05/005"},{"time":1.1667,"name":"爆炸_05/006"},{"time":1.2,"name":"爆炸_05/007"},{"time":1.2333,"name":"爆炸_05/008"},{"time":1.2667,"name":"爆炸_05/009"},{"time":1.3,"name":"爆炸_05/010"},{"time":1.3333,"name":"爆炸_05/001"},{"time":1.3667,"name":"爆炸_05/002"},{"time":1.4,"name":"爆炸_05/003"},{"time":1.4333,"name":"爆炸_05/004"},{"time":1.4667,"name":"爆炸_05/005"},{"time":1.5,"name":"爆炸_05/006"},{"time":1.5333,"name":"爆炸_05/007"},{"time":1.5667,"name":"爆炸_05/008"},{"time":1.6,"name":"爆炸_05/009"},{"time":1.6333,"name":"爆炸_05/010"},{"time":1.6667,"name":"爆炸_05/001"},{"time":1.7,"name":"爆炸_05/002"},{"time":1.7333,"name":"爆炸_05/003"},{"time":1.7667,"name":"爆炸_05/004"},{"time":1.8,"name":"爆炸_05/005"},{"time":1.8333,"name":"爆炸_05/006"},{"time":1.8667,"name":"爆炸_05/007"},{"time":1.9,"name":"爆炸_05/008"},{"time":1.9333,"name":"爆炸_05/009"},{"time":1.9667,"name":"爆炸_05/010"}]},"sparkA":{"attachment":[{"name":"sparkA"}]},"WIN_Seq":{"attachment":[{"time":0.8333,"name":"WIN_Seq/Comp 1_00000"},{"time":0.8667,"name":"WIN_Seq/Comp 1_00001"},{"time":0.9,"name":"WIN_Seq/Comp 1_00002"},{"time":0.9333,"name":"WIN_Seq/Comp 1_00003"},{"time":0.9667,"name":"WIN_Seq/Comp 1_00004"},{"time":1,"name":"WIN_Seq/Comp 1_00005"},{"time":1.0333,"name":"WIN_Seq/Comp 1_00006"},{"time":1.0667,"name":"WIN_Seq/Comp 1_00007"},{"time":1.1,"name":"WIN_Seq/Comp 1_00008"},{"time":1.1333,"name":"WIN_Seq/Comp 1_00009"},{"time":1.1667,"name":"WIN_Seq/Comp 1_00010"},{"time":1.2,"name":"WIN_Seq/Comp 1_00011"},{"time":1.2333,"name":"WIN_Seq/Comp 1_00012"},{"time":1.2667,"name":"WIN_Seq/Comp 1_00013"},{"time":1.3,"name":"WIN_Seq/Comp 1_00014"},{"time":1.3333,"name":"WIN_Seq/Comp 1_00015"},{"time":1.3667,"name":"WIN_Seq/Comp 1_00016"},{"time":1.4,"name":"WIN_Seq/Comp 1_00017"},{"time":1.4333,"name":"WIN_Seq/Comp 1_00018"},{"time":1.4667,"name":"WIN_Seq/Comp 1_00019"},{"time":1.5,"name":"WIN_Seq/Comp 1_00020"},{"time":1.5333,"name":"WIN_Seq/Comp 1_00021"},{"time":1.5667,"name":"WIN_Seq/Comp 1_00022"},{"time":1.6,"name":"WIN_Seq/Comp 1_00023"},{"time":1.6333,"name":"WIN_Seq/Comp 1_00024"},{"time":1.6667,"name":"WIN_Seq/Comp 1_00025"},{"time":1.7,"name":"WIN_Seq/Comp 1_00026"},{"time":1.7333,"name":"WIN_Seq/Comp 1_00027"},{"time":1.7667,"name":"WIN_Seq/Comp 1_00028"},{"time":1.8,"name":null}]},"sparkB":{"attachment":[{"name":"sparkB"}]},"sparkA2":{"color":[{"color":"ffffff00","curve":"stepped"},{"time":0.0333,"color":"ffffff00"},{"time":0.0667,"color":"ffffff7e"},{"time":0.1,"color":"ffffff00","curve":"stepped"},{"time":0.1667,"color":"ffffff00"},{"time":0.2,"color":"ffffff7e"},{"time":0.2333,"color":"ffffff00","curve":"stepped"},{"time":0.3,"color":"ffffff00"},{"time":0.3333,"color":"ffffff7e"},{"time":0.3667,"color":"ffffff00","curve":"stepped"},{"time":0.4333,"color":"ffffff00"},{"time":0.4667,"color":"ffffff7e"},{"time":0.5,"color":"ffffff00","curve":"stepped"},{"time":0.5667,"color":"ffffff00"},{"time":0.6,"color":"ffffff7e"},{"time":0.6333,"color":"ffffff00","curve":"stepped"},{"time":0.7,"color":"ffffff00"},{"time":0.7333,"color":"ffffff7e"},{"time":0.7667,"color":"ffffff00","curve":"stepped"},{"time":0.8333,"color":"ffffff00"},{"time":0.8667,"color":"ffffff7e"},{"time":0.9,"color":"ffffff00","curve":"stepped"},{"time":0.9667,"color":"ffffff00"},{"time":1,"color":"ffffff7e"},{"time":1.0333,"color":"ffffff00","curve":"stepped"},{"time":1.1,"color":"ffffff00"},{"time":1.1333,"color":"ffffff7e"},{"time":1.1667,"color":"ffffff00","curve":"stepped"},{"time":1.2333,"color":"ffffff00"},{"time":1.2667,"color":"ffffff7e"},{"time":1.3,"color":"ffffff00","curve":"stepped"},{"time":1.3333,"color":"ffffff00"},{"time":1.3667,"color":"ffffff7e"},{"time":1.4,"color":"ffffff00","curve":"stepped"},{"time":1.4667,"color":"ffffff00"},{"time":1.5,"color":"ffffff7e"},{"time":1.5333,"color":"ffffff00","curve":"stepped"},{"time":1.5667,"color":"ffffff00"},{"time":1.6,"color":"ffffff7e"},{"time":1.6333,"color":"ffffff00","curve":"stepped"},{"time":1.7,"color":"ffffff00"},{"time":1.7333,"color":"ffffff7e"},{"time":1.7667,"color":"ffffff00","curve":"stepped"},{"time":1.8333,"color":"ffffff00"},{"time":1.8667,"color":"ffffff7e"},{"time":1.9,"color":"ffffff00"}],"attachment":[{"name":"sparkA"}]},"SMZ02":{"attachment":[{"name":"SMZ02"}]},"SMZ01":{"attachment":[{"name":"SMZ01"}]},"GF02":{"color":[{"color":"ffffff00","curve":0,"c2":0.29,"c3":0.75},{"time":0.5,"color":"ffffffff","curve":0.25,"c3":0.75},{"time":1,"color":"ffffff00"}],"attachment":[{"name":"GF02"}]},"firecrA":{"attachment":[{"name":"firecrA"}]},"Jew02":{"attachment":[{"name":"Jew02"}]},"2_WIN2":{"color":[{"color":"ffffff00","curve":"stepped"},{"time":0.6667,"color":"ffffff00","curve":0,"c2":0.29,"c3":0.75},{"time":1.3333,"color":"ffffff66","curve":0.25,"c3":0.75},{"time":2,"color":"ffffff00"}],"attachment":[{"name":"WIN"}]},"Jew03":{"attachment":[{"name":"Jew03"}]},"RedLig3":{"color":[{"color":"ffffff00"},{"time":0.5,"color":"ffffff6e"},{"time":1,"color":"ffffff00"}],"attachment":[{"name":"PZ001"}]},"firecrB":{"attachment":[{"name":"firecrB"}]},"BAO_Left":{"attachment":[{"name":"BAO_Left"}]},"glow":{"color":[{"color":"ff9c5d00","curve":0.25,"c3":0.75},{"time":1,"color":"ff9c5da5","curve":0.25,"c3":0.75},{"time":2,"color":"ff9c5d00"}],"attachment":[{"name":"glow"}]},"Icon_Common_24":{"color":[{"color":"ffffff00","curve":0,"c2":0.3,"c3":0.75},{"time":0.5,"color":"f8b025c5","curve":0.25,"c3":0.75},{"time":1,"color":"ffffff00"}],"attachment":[{"name":"Icon_Common_24"}]},"BAO_Right":{"attachment":[{"name":"BAO_Right"}]}},"bones":{"1_MEGA":{"scale":[{"curve":0,"c2":0.29,"c3":0.75},{"time":0.6667,"x":1.2,"y":1.2,"curve":0.25,"c3":0.75},{"time":1.3333}]},"2_WIN":{"scale":[{"time":0.6667,"curve":0,"c2":0.29,"c3":0.75},{"time":1.3333,"x":1.2,"y":1.2,"curve":0.25,"c3":0.75},{"time":2}]},"3_Left_gold":{"rotate":[{"curve":0,"c2":0.3,"c3":0.75},{"time":0.5,"angle":2.9,"curve":0.25,"c3":0.75},{"time":1}],"translate":[{"curve":0,"c2":0.3,"c3":0.75},{"time":0.5,"x":-45.49,"y":73.92,"curve":0.25,"c3":0.75},{"time":1}],"scale":[{"curve":0,"c2":0.3,"c3":0.75},{"time":0.5,"x":1.08,"y":1.284,"curve":0.25,"c3":0.75},{"time":1}]},"4_Right_gold":{"rotate":[{"time":0.1667,"curve":0,"c2":0.3,"c3":0.75},{"time":0.6667,"angle":-13.29,"curve":0.25,"c3":0.75},{"time":1.1667}],"translate":[{"time":0.1667,"curve":0,"c2":0.3,"c3":0.75},{"time":0.6667,"x":58.28,"y":75.77,"curve":0.25,"c3":0.75},{"time":1.1667}],"scale":[{"time":0.1667,"curve":0,"c2":0.3,"c3":0.75},{"time":0.6667,"x":1.08,"y":1.284,"curve":0.25,"c3":0.75},{"time":1.1667}]},"LigDot_Left":{"scale":[{"x":0,"y":0,"curve":0,"c2":0.3,"c3":0.75},{"time":1,"x":1.412,"y":1.412}]},"LigDot_Right":{"scale":[{"x":0,"y":0,"curve":0,"c2":0.29,"c3":0.75},{"time":1,"x":1.412,"y":1.412}]},"Icon_Common_24":{"scale":[{"curve":0,"c2":0.3,"c3":0.75},{"time":1,"x":3,"y":3}]},"glow":{"rotate":[{"curve":0.25,"c3":0.75},{"time":2,"angle":-90}],"scale":[{"x":5.117,"y":5.117}]},"RedLig2":{"scale":[{},{"time":2,"x":1.5,"y":1.5}]},"RedLig":{"scale":[{},{"time":2,"x":1.5,"y":1.5}]},"RedLig3":{"scale":[{},{"time":1,"x":1.5,"y":1.5}]},"RedLig4":{"scale":[{},{"time":1,"x":1.5,"y":1.5}]},"5_Left_SMZ2":{"rotate":[{"curve":0,"c2":0.3,"c3":0.75},{"time":0.8333,"angle":22.21,"curve":0.25,"c3":0.75},{"time":1.6667}],"translate":[{"curve":0,"c2":0.3,"c3":0.75},{"time":0.8333,"x":-38.81,"y":14.93,"curve":0.25,"c3":0.75},{"time":1.6667}]},"6_Right_SMZ":{"rotate":[{"curve":0,"c2":0.3,"c3":0.75},{"time":0.8333,"angle":-19.73,"curve":0.25,"c3":0.75},{"time":1.6667}],"translate":[{"curve":0,"c2":0.3,"c3":0.75},{"time":0.8333,"x":73.4,"curve":0.25,"c3":0.75},{"time":1.6667}]},"All3":{"rotate":[{},{"time":0.5,"angle":8.46},{"time":1}],"translate":[{},{"time":0.5,"x":12.63,"y":33.76},{"time":1}]},"All4":{"rotate":[{},{"time":0.5,"angle":8.46},{"time":1}]},"8_Right_pao":{"rotate":[{"curve":0,"c2":0.3,"c3":0.75},{"time":0.5,"angle":-8.99,"curve":0.25,"c3":0.75},{"time":1}],"translate":[{"curve":0,"c2":0.3,"c3":0.75},{"time":0.5,"x":3.84,"y":-3.09,"curve":0.25,"c3":0.75},{"time":1}]},"All13":{"rotate":[{"curve":0,"c2":0.3,"c3":0.75},{"time":0.5,"angle":-8.99,"curve":0.25,"c3":0.75},{"time":1}]},"All12":{"rotate":[{"curve":0,"c2":0.3,"c3":0.75},{"time":0.5,"angle":-8.99,"curve":0.25,"c3":0.75},{"time":1}]},"All11":{"rotate":[{"curve":0,"c2":0.3,"c3":0.75},{"time":0.5,"angle":-8.99,"curve":0.25,"c3":0.75},{"time":1}]},"All10":{"rotate":[{"curve":0,"c2":0.3,"c3":0.75},{"time":0.5,"angle":-8.99,"curve":0.25,"c3":0.75},{"time":1}]},"All9":{"rotate":[{"curve":0,"c2":0.3,"c3":0.75},{"time":0.5,"angle":-8.99,"curve":0.25,"c3":0.75},{"time":1}]},"SPARK_Lrft":{"scale":[{"time":0.0333},{"time":0.0667,"x":1.1,"y":1.1},{"time":0.1,"curve":"stepped"},{"time":0.1667},{"time":0.2,"x":1.1,"y":1.1},{"time":0.2333,"curve":"stepped"},{"time":0.3},{"time":0.3333,"x":1.1,"y":1.1},{"time":0.3667,"curve":"stepped"},{"time":0.4333},{"time":0.4667,"x":1.1,"y":1.1},{"time":0.5,"curve":"stepped"},{"time":0.5667},{"time":0.6,"x":1.1,"y":1.1},{"time":0.6333,"curve":"stepped"},{"time":0.7},{"time":0.7333,"x":1.1,"y":1.1},{"time":0.7667,"curve":"stepped"},{"time":0.8333},{"time":0.8667,"x":1.1,"y":1.1},{"time":0.9,"curve":"stepped"},{"time":0.9667},{"time":1,"x":1.1,"y":1.1},{"time":1.0333,"curve":"stepped"},{"time":1.1},{"time":1.1333,"x":1.1,"y":1.1},{"time":1.1667,"curve":"stepped"},{"time":1.2333},{"time":1.2667,"x":1.1,"y":1.1},{"time":1.3,"curve":"stepped"},{"time":1.3333},{"time":1.3667,"x":1.1,"y":1.1},{"time":1.4,"curve":"stepped"},{"time":1.4667},{"time":1.5,"x":1.1,"y":1.1},{"time":1.5333,"curve":"stepped"},{"time":1.5667},{"time":1.6,"x":1.1,"y":1.1},{"time":1.6333,"curve":"stepped"},{"time":1.7},{"time":1.7333,"x":1.1,"y":1.1},{"time":1.7667,"curve":"stepped"},{"time":1.8333},{"time":1.8667,"x":1.1,"y":1.1},{"time":1.9}]},"SPARK_Lrft3":{"scale":[{"x":0.585,"y":0.585}]},"骨骼2":{"scale":[{"time":0.0333},{"time":0.0667,"x":1.1,"y":1.1},{"time":0.1,"curve":"stepped"},{"time":0.1667},{"time":0.2,"x":1.1,"y":1.1},{"time":0.2333,"curve":"stepped"},{"time":0.3},{"time":0.3333,"x":1.1,"y":1.1},{"time":0.3667,"curve":"stepped"},{"time":0.4333},{"time":0.4667,"x":1.1,"y":1.1},{"time":0.5,"curve":"stepped"},{"time":0.5667},{"time":0.6,"x":1.1,"y":1.1},{"time":0.6333,"curve":"stepped"},{"time":0.7},{"time":0.7333,"x":1.1,"y":1.1},{"time":0.7667,"curve":"stepped"},{"time":0.8333},{"time":0.8667,"x":1.1,"y":1.1},{"time":0.9,"curve":"stepped"},{"time":0.9667},{"time":1,"x":1.1,"y":1.1},{"time":1.0333,"curve":"stepped"},{"time":1.1},{"time":1.1333,"x":1.1,"y":1.1},{"time":1.1667,"curve":"stepped"},{"time":1.2333},{"time":1.2667,"x":1.1,"y":1.1},{"time":1.3,"curve":"stepped"},{"time":1.3333},{"time":1.3667,"x":1.1,"y":1.1},{"time":1.4,"curve":"stepped"},{"time":1.4667},{"time":1.5,"x":1.1,"y":1.1},{"time":1.5333,"curve":"stepped"},{"time":1.5667},{"time":1.6,"x":1.1,"y":1.1},{"time":1.6333,"curve":"stepped"},{"time":1.7},{"time":1.7333,"x":1.1,"y":1.1},{"time":1.7667,"curve":"stepped"},{"time":1.8333},{"time":1.8667,"x":1.1,"y":1.1},{"time":1.9}]},"骨骼3":{"scale":[{"x":0.585,"y":0.585}]}}},"out":{"slots":{"1_MEGA":{"color":[{"time":0.3333,"color":"ffffffff"},{"time":0.5,"color":"ffffff00"}],"attachment":[{"name":"MEGA"}]},"2_WIN":{"color":[{"time":0.3333,"color":"ffffffff"},{"time":0.5,"color":"ffffff00"}],"attachment":[{"name":"WIN"}]},"sparkA2":{"color":[{"time":0.3333,"color":"ffffffff"},{"time":0.5,"color":"ffffff00"}],"attachment":[{"name":"sparkA"}]},"Jew01":{"color":[{"time":0.3333,"color":"ffffffff","curve":0.25,"c3":0.75},{"time":0.5,"color":"ffffff00"}],"attachment":[{"name":"Jew01"}]},"sparkB":{"color":[{"time":0.3333,"color":"ffffffff"},{"time":0.5,"color":"ffffff00"}],"attachment":[{"name":"sparkB"}]},"SMZ02":{"color":[{"time":0.3333,"color":"ffffffff","curve":0.25,"c3":0.75},{"time":0.5,"color":"ffffff00"}],"attachment":[{"name":"SMZ02"}]},"SMZ01":{"color":[{"time":0.3333,"color":"ffffffff","curve":0.25,"c3":0.75},{"time":0.5,"color":"ffffff00"}],"attachment":[{"name":"SMZ01"}]},"firecrA":{"color":[{"time":0.3333,"color":"ffffffff","curve":0.25,"c3":0.75},{"time":0.5,"color":"ffffff00"}],"attachment":[{"name":"firecrA"}]},"Jew02":{"color":[{"time":0.3333,"color":"ffffffff","curve":0.25,"c3":0.75},{"time":0.5,"color":"ffffff00"}],"attachment":[{"name":"Jew02"}]},"Jew03":{"color":[{"time":0.3333,"color":"ffffffff","curve":0.25,"c3":0.75},{"time":0.5,"color":"ffffff00"}],"attachment":[{"name":"Jew03"}]},"sparkA":{"color":[{"time":0.3333,"color":"ffffffff"},{"time":0.5,"color":"ffffff00"}],"attachment":[{"name":"sparkA"}]},"firecrB":{"color":[{"time":0.3333,"color":"ffffffff","curve":0.25,"c3":0.75},{"time":0.5,"color":"ffffff00"}],"attachment":[{"name":"firecrB"}]},"BAO_Left":{"color":[{"time":0.3333,"color":"ffffffff"},{"time":0.5,"color":"ffffff00"}],"attachment":[{"name":"BAO_Left"}]},"BAO_Right":{"color":[{"time":0.3333,"color":"ffffffff"},{"time":0.5,"color":"ffffff00"}],"attachment":[{"name":"BAO_Right"}]}},"bones":{"All":{"scale":[{"curve":0.25,"c3":0.75},{"time":0.3333,"x":1.2,"y":1.2,"curve":0.25,"c3":0.75},{"time":0.8333,"x":0,"y":0}]}}}}}