{"skeleton":{"hash":"Ac+OC7rqQc2SXAjZTuGkodqxLyE","spine":"3.8.72","x":-511,"y":-372,"width":984,"height":685,"images":"./images/","audio":"C:/設計區/胖達專案區/多福多財/4_動態特效/SPINE/EditFiles/Item_MG_Bowl"},"bones":[{"name":"root"},{"name":"All","parent":"root"},{"name":"招財進寶_文字","parent":"All"},{"name":"招財進寶_財寶","parent":"All"},{"name":"cover_01","parent":"All"},{"name":"old","parent":"招財進寶_財寶"},{"name":"Lig_Effect_All","parent":"root","color":"faff00ff"},{"name":"LigDot_Seq","parent":"Lig_Effect_All","y":-46.37,"scaleX":12.5481,"scaleY":12.5481,"color":"faff00ff"},{"name":"Explo_SeqA","parent":"Lig_Effect_All","color":"faff00ff"},{"name":"Explo_SeqB","parent":"Lig_Effect_All","color":"faff00ff"},{"name":"LigDots","parent":"Lig_Effect_All","color":"faff00ff"},{"name":"LigDot01","parent":"LigDots","color":"faff00ff"},{"name":"Icon_Common_24","parent":"Lig_Effect_All","color":"faff00ff"},{"name":"LigDot1","parent":"LigDots","color":"faff00ff"},{"name":"LigDot2","parent":"LigDots","color":"faff00ff"},{"name":"LigDot3","parent":"LigDots","color":"faff00ff"},{"name":"招財進寶_文字_LIG","parent":"All"},{"name":"招財進寶_財寶_LIG","parent":"All"},{"name":"old2","parent":"招財進寶_財寶_LIG"},{"name":"cover_Lig","parent":"All"}],"slots":[{"name":"bm","bone":"root"},{"name":"pot_05","bone":"All","attachment":"pot_05"},{"name":"pot_Lig","bone":"All","blend":"additive"},{"name":"pot_04","bone":"old"},{"name":"pot_4","bone":"old2"},{"name":"pot_03","bone":"old"},{"name":"pot_3","bone":"old2"},{"name":"pot_02","bone":"old"},{"name":"pot_2","bone":"old2"},{"name":"pot_01","bone":"old"},{"name":"pot_1","bone":"old2"},{"name":"all","bone":"All","attachment":"all"},{"name":"all_Lig","bone":"All","blend":"additive"},{"name":"cover_02","bone":"cover_01"},{"name":"cover_2","bone":"cover_Lig","blend":"additive"},{"name":"招","bone":"招財進寶_文字","attachment":"招"},{"name":"招2","bone":"招財進寶_文字_LIG","blend":"additive"},{"name":"財","bone":"招財進寶_文字","attachment":"財"},{"name":"財2","bone":"招財進寶_文字_LIG","blend":"additive"},{"name":"進","bone":"招財進寶_文字","attachment":"進"},{"name":"進2","bone":"招財進寶_文字_LIG","blend":"additive"},{"name":"寶","bone":"招財進寶_文字","attachment":"寶"},{"name":"寶2","bone":"招財進寶_文字_LIG","blend":"additive"},{"name":"招_財寶","bone":"招財進寶_財寶","attachment":"招_財寶"},{"name":"招_財寶2","bone":"招財進寶_財寶_LIG","blend":"additive"},{"name":"招財_財寶","bone":"招財進寶_財寶","attachment":"招財_財寶"},{"name":"招財_財寶2","bone":"招財進寶_財寶_LIG","blend":"additive"},{"name":"招財進_財寶","bone":"招財進寶_財寶","attachment":"招財進_財寶"},{"name":"招財進_財寶2","bone":"招財進寶_財寶_LIG","blend":"additive"},{"name":"招財進寶_財寶","bone":"招財進寶_財寶","attachment":"招財進寶_財寶"},{"name":"招財進寶_財寶_LIG","bone":"招財進寶_財寶_LIG","blend":"additive"},{"name":"cover_01","bone":"cover_01"},{"name":"cover_Lig","bone":"cover_Lig","blend":"additive"},{"name":"LigDot_Seq","bone":"LigDot_Seq","color":"ffbf00ff","blend":"additive"},{"name":"Explo_SeqA","bone":"Explo_SeqA","blend":"additive"},{"name":"Explo_SeqB","bone":"Explo_SeqB","blend":"additive"},{"name":"LigDot01","bone":"LigDot01","blend":"additive"},{"name":"LigDot1","bone":"LigDot1","blend":"additive"},{"name":"LigDot2","bone":"LigDot2","blend":"additive"},{"name":"LigDot3","bone":"LigDot3","blend":"additive"},{"name":"Icon_Common_24","bone":"Icon_Common_24","blend":"additive"}],"skins":[{"name":"default","attachments":{"pot_Lig":{"pot_05":{"x":-19,"y":-111,"width":984,"height":522}},"Explo_SeqA":{"火焰爆炸合/Explo_A_00000":{"width":320,"height":180},"火焰爆炸合/Explo_A_00001":{"width":320,"height":180},"火焰爆炸合/Explo_A_00002":{"width":320,"height":180},"火焰爆炸合/Explo_A_00003":{"width":320,"height":180},"火焰爆炸合/Explo_A_00004":{"width":320,"height":180},"火焰爆炸合/Explo_A_00005":{"width":320,"height":180},"火焰爆炸合/Explo_A_00006":{"width":320,"height":180},"火焰爆炸合/Explo_A_00007":{"width":320,"height":180},"火焰爆炸合/Explo_A_00008":{"width":320,"height":180},"火焰爆炸合/Explo_A_00009":{"width":320,"height":180},"火焰爆炸合/Explo_A_00010":{"width":320,"height":180},"火焰爆炸合/Explo_A_00011":{"width":320,"height":180},"火焰爆炸合/Explo_A_00012":{"width":320,"height":180},"火焰爆炸合/Explo_A_00013":{"width":320,"height":180},"火焰爆炸合/Explo_A_00014":{"width":320,"height":180},"火焰爆炸合/Explo_A_00015":{"width":320,"height":180},"火焰爆炸合/Explo_A_00016":{"width":320,"height":180},"火焰爆炸合/Explo_A_00017":{"width":320,"height":180},"火焰爆炸合/Explo_A_00018":{"width":320,"height":180},"火焰爆炸合/Explo_A_00019":{"width":320,"height":180},"火焰爆炸合/Explo_A_00020":{"width":320,"height":180},"火焰爆炸合/Explo_A_00021":{"width":320,"height":180},"火焰爆炸合/Explo_A_00022":{"width":320,"height":180},"火焰爆炸合/Explo_A_00023":{"width":320,"height":180},"火焰爆炸合/Explo_A_00024":{"width":320,"height":180},"火焰爆炸合/Explo_A_00025":{"width":320,"height":180},"火焰爆炸合/Explo_A_00026":{"width":320,"height":180},"火焰爆炸合/Explo_A_00027":{"width":320,"height":180},"火焰爆炸合/Explo_A_00028":{"width":320,"height":180},"火焰爆炸合/Explo_A_00029":{"width":320,"height":180},"火焰爆炸合/Explo_A_00030":{"width":320,"height":180},"火焰爆炸合/Explo_A_00031":{"width":320,"height":180},"火焰爆炸合/Explo_A_00032":{"width":320,"height":180},"火焰爆炸合/Explo_A_00033":{"width":320,"height":180},"火焰爆炸合/Explo_A_00034":{"width":320,"height":180},"火焰爆炸合/Explo_A_00035":{"width":320,"height":180},"火焰爆炸合/Explo_A_00036":{"width":320,"height":180},"火焰爆炸合/Explo_A_00037":{"width":320,"height":180},"火焰爆炸合/Explo_A_00038":{"width":320,"height":180},"火焰爆炸合/Explo_A_00039":{"width":320,"height":180},"火焰爆炸合/Explo_A_00040":{"width":320,"height":180},"火焰爆炸合/Explo_A_00041":{"width":320,"height":180},"火焰爆炸合/Explo_A_00042":{"width":320,"height":180},"火焰爆炸合/Explo_A_00043":{"width":320,"height":180},"火焰爆炸合/Explo_A_00044":{"width":320,"height":180},"火焰爆炸合/Explo_A_00045":{"width":320,"height":180},"火焰爆炸合/Explo_A_00046":{"width":320,"height":180},"火焰爆炸合/Explo_A_00047":{"width":320,"height":180},"火焰爆炸合/Explo_A_00048":{"width":320,"height":180},"火焰爆炸合/Explo_A_00049":{"width":320,"height":180},"火焰爆炸合/Explo_A_00050":{"width":320,"height":180},"火焰爆炸合/Explo_A_00051":{"width":320,"height":180},"火焰爆炸合/Explo_A_00052":{"width":320,"height":180},"火焰爆炸合/Explo_A_00053":{"width":320,"height":180},"火焰爆炸合/Explo_A_00054":{"width":320,"height":180},"火焰爆炸合/Explo_A_00055":{"width":320,"height":180},"火焰爆炸合/Explo_A_00056":{"width":320,"height":180},"火焰爆炸合/Explo_A_00057":{"width":320,"height":180},"火焰爆炸合/Explo_A_00058":{"width":320,"height":180},"火焰爆炸合/Explo_A_00059":{"width":320,"height":180},"火焰爆炸合/Explo_A_00060":{"width":320,"height":180},"火焰爆炸合/Explo_A_00061":{"width":320,"height":180},"火焰爆炸合/Explo_A_00062":{"width":320,"height":180},"火焰爆炸合/Explo_A_00063":{"width":320,"height":180},"火焰爆炸合/Explo_A_00064":{"width":320,"height":180},"火焰爆炸合/Explo_A_00065":{"width":320,"height":180},"火焰爆炸合/Explo_A_00066":{"width":320,"height":180},"火焰爆炸合/Explo_A_00067":{"width":320,"height":180}},"Explo_SeqB":{"爆炸_05/001":{"x":0.5,"y":0.5,"width":121,"height":119},"爆炸_05/002":{"x":0.5,"width":131,"height":130},"爆炸_05/003":{"x":0.5,"width":173,"height":172},"爆炸_05/004":{"x":0.5,"width":205,"height":206},"爆炸_05/005":{"x":0.5,"y":0.5,"width":229,"height":233},"爆炸_05/006":{"width":240,"height":244},"爆炸_05/007":{"x":0.5,"width":237,"height":256},"爆炸_05/008":{"y":0.5,"width":250,"height":265},"爆炸_05/009":{"x":0.5,"width":259,"height":250},"爆炸_05/010":{"width":260,"height":250}},"pot_1":{"pot_01":{"type":"mesh","uvs":[1,1,0,1,0,0,1,0],"triangles":[1,2,3,1,3,0],"vertices":[246,-54,-320,-54,-320,45,246,45],"hull":4,"edges":[0,2,2,4,4,6,0,6],"width":566,"height":99}},"pot_2":{"pot_02":{"type":"mesh","uvs":[1,1,0,1,0,0,1,0],"triangles":[1,2,3,1,3,0],"vertices":[352,-54,-383,-54,-383,88,352,88],"hull":4,"edges":[0,2,2,4,4,6,0,6],"width":735,"height":142}},"cover_01":{"cover_01":{"x":47,"y":131,"width":926,"height":480}},"pot_4":{"pot_04":{"type":"mesh","uvs":[1,1,0,1,0,0,1,0],"triangles":[1,2,3,1,3,0],"vertices":[379,-54,-413,-54,-413,313,379,313],"hull":4,"edges":[0,2,2,4,4,6,0,6],"width":792,"height":367}},"bm":{"bm":{"y":-0.5,"width":1022,"height":747}},"all_Lig":{"all":{"x":-25.5,"y":-197.5,"width":855,"height":255}},"Icon_Common_24":{"Icon_Common_24":{"width":512,"height":512}},"LigDot1":{"LigDot01":{"y":0.5,"width":146,"height":117}},"LigDot2":{"LigDot01":{"y":0.5,"width":146,"height":117}},"LigDot3":{"LigDot01":{"y":0.5,"width":146,"height":117}},"cover_02":{"cover_02":{"x":41.5,"y":85.5,"width":913,"height":229}},"all":{"all":{"x":-25.5,"y":-197.5,"width":855,"height":255}},"cover_Lig":{"cover_01":{"x":47,"y":131,"width":926,"height":480}},"cover_2":{"cover_02":{"x":41.5,"y":85.5,"width":913,"height":229}},"pot_01":{"pot_01":{"type":"mesh","uvs":[1,1,0,1,0,0,1,0],"triangles":[1,2,3,1,3,0],"vertices":[246,-54,-320,-54,-320,45,246,45],"hull":4,"edges":[0,2,2,4,4,6,0,6],"width":566,"height":99}},"pot_02":{"pot_02":{"type":"mesh","uvs":[1,1,0,1,0,0,1,0],"triangles":[1,2,3,1,3,0],"vertices":[352,-54,-383,-54,-383,88,352,88],"hull":4,"edges":[0,2,2,4,4,6,0,6],"width":735,"height":142}},"pot_03":{"pot_03":{"type":"mesh","uvs":[1,1,0,1,0,0,1,0],"triangles":[1,2,3,1,3,0],"vertices":[366,-54,-407,-54,-407,131,366,131],"hull":4,"edges":[0,2,2,4,4,6,0,6],"width":773,"height":185}},"pot_04":{"pot_04":{"type":"mesh","uvs":[1,1,0,1,0,0,1,0],"triangles":[1,2,3,1,3,0],"vertices":[379,-54,-413,-54,-413,313,379,313],"hull":4,"edges":[0,2,2,4,4,6,0,6],"width":792,"height":367}},"pot_05":{"pot_05":{"x":-19,"y":-111,"width":984,"height":522}},"pot_3":{"pot_03":{"type":"mesh","uvs":[1,1,0,1,0,0,1,0],"triangles":[1,2,3,1,3,0],"vertices":[366,-54,-407,-54,-407,131,366,131],"hull":4,"edges":[0,2,2,4,4,6,0,6],"width":773,"height":185}},"LigDot01":{"LigDot01":{"y":0.5,"width":146,"height":117}},"LigDot_Seq":{"光點_02/3_00001":{"x":0.5,"y":0.5,"width":73,"height":77},"光點_02/3_00002":{"x":0.5,"y":0.5,"width":73,"height":77},"光點_02/3_00003":{"x":0.5,"y":0.5,"width":73,"height":77},"光點_02/3_00004":{"x":0.5,"y":0.5,"width":73,"height":77},"光點_02/3_00005":{"x":0.5,"y":0.5,"width":73,"height":77},"光點_02/3_00006":{"x":0.5,"y":0.5,"width":73,"height":77},"光點_02/3_00007":{"x":0.5,"y":0.5,"width":73,"height":77},"光點_02/3_00008":{"x":0.5,"y":0.5,"width":73,"height":77},"光點_02/3_00009":{"x":0.5,"y":0.5,"width":73,"height":77},"光點_02/3_00010":{"x":0.5,"y":0.5,"width":73,"height":77},"光點_02/3_00011":{"x":0.5,"y":0.5,"width":73,"height":77},"光點_02/3_00012":{"x":0.5,"y":0.5,"width":73,"height":77},"光點_02/3_00013":{"x":0.5,"y":0.5,"width":73,"height":77},"光點_02/3_00014":{"x":0.5,"y":0.5,"width":73,"height":77},"光點_02/3_00015":{"x":0.5,"y":0.5,"width":73,"height":77},"光點_02/3_00016":{"x":0.5,"y":0.5,"width":73,"height":77},"光點_02/3_00017":{"x":0.5,"y":0.5,"width":73,"height":77},"光點_02/3_00018":{"x":0.5,"y":0.5,"width":73,"height":77},"光點_02/3_00019":{"x":0.5,"y":0.5,"width":73,"height":77},"光點_02/3_00020":{"x":0.5,"y":0.5,"width":73,"height":77},"光點_02/3_00021":{"x":0.5,"y":0.5,"width":73,"height":77},"光點_02/3_00022":{"x":0.5,"y":0.5,"width":73,"height":77},"光點_02/3_00023":{"x":0.5,"y":0.5,"width":73,"height":77},"光點_02/3_00024":{"x":0.5,"y":0.5,"width":73,"height":77},"光點_02/3_00025":{"x":0.5,"y":0.5,"width":73,"height":77},"光點_02/3_00026":{"x":0.5,"y":0.5,"width":73,"height":77},"光點_02/3_00027":{"x":0.5,"y":0.5,"width":73,"height":77},"光點_02/3_00028":{"x":0.5,"y":0.5,"width":73,"height":77},"光點_02/3_00029":{"x":0.5,"y":0.5,"width":73,"height":77}}}},{"name":"招","attachments":{"招_財寶":{"招_財寶":{"name":"pot_01","type":"mesh","uvs":[1,1,0,1,0,0,1,0],"triangles":[1,2,3,1,3,0],"vertices":[246,-54,-320,-54,-320,45,246,45],"hull":4,"edges":[0,2,2,4,4,6,0,6],"width":566,"height":99}},"招":{"招":{"name":"fo_01","type":"mesh","uvs":[1,1,0,1,0,0,1,0],"triangles":[1,2,3,1,3,0],"vertices":[-238,-267,-453,-267,-453,-69,-238,-69],"hull":4,"edges":[0,2,2,4,4,6,0,6],"width":215,"height":198}},"招2":{"招":{"name":"fo_01","type":"mesh","uvs":[1,1,0,1,0,0,1,0],"triangles":[1,2,3,1,3,0],"vertices":[-238,-267,-453,-267,-453,-69,-238,-69],"hull":4,"edges":[0,2,2,4,4,6,0,6],"width":215,"height":198}},"招_財寶2":{"招_財寶":{"name":"pot_01","type":"mesh","uvs":[1,1,0,1,0,0,1,0],"triangles":[1,2,3,1,3,0],"vertices":[246,-54,-320,-54,-320,45,246,45],"hull":4,"edges":[0,2,2,4,4,6,0,6],"width":566,"height":99}}}},{"name":"招財","attachments":{"招財_財寶2":{"招財_財寶":{"name":"pot_02","type":"mesh","uvs":[1,1,0,1,0,0,1,0],"triangles":[1,2,3,1,3,0],"vertices":[352,-54,-383,-54,-383,88,352,88],"hull":4,"edges":[0,2,2,4,4,6,0,6],"width":735,"height":142}},"招":{"招":{"name":"fo_01","type":"mesh","uvs":[1,1,0,1,0,0,1,0],"triangles":[1,2,3,1,3,0],"vertices":[-238,-267,-453,-267,-453,-69,-238,-69],"hull":4,"edges":[0,2,2,4,4,6,0,6],"width":215,"height":198}},"財":{"財":{"name":"fo_02","type":"mesh","uvs":[1,1,0,1,0,0,1,0],"triangles":[1,2,3,1,3,0],"vertices":[-26,-325,-258,-325,-258,-111,-26,-111],"hull":4,"edges":[0,2,2,4,4,6,0,6],"width":232,"height":214}},"招財_財寶":{"招財_財寶":{"name":"pot_02","type":"mesh","uvs":[1,1,0,1,0,0,1,0],"triangles":[1,2,3,1,3,0],"vertices":[352,-54,-383,-54,-383,88,352,88],"hull":4,"edges":[0,2,2,4,4,6,0,6],"width":735,"height":142}},"財2":{"財":{"name":"fo_02","type":"mesh","uvs":[1,1,0,1,0,0,1,0],"triangles":[1,2,3,1,3,0],"vertices":[-26,-325,-258,-325,-258,-111,-26,-111],"hull":4,"edges":[0,2,2,4,4,6,0,6],"width":232,"height":214}},"招2":{"招":{"name":"fo_01","type":"mesh","uvs":[1,1,0,1,0,0,1,0],"triangles":[1,2,3,1,3,0],"vertices":[-238,-267,-453,-267,-453,-69,-238,-69],"hull":4,"edges":[0,2,2,4,4,6,0,6],"width":215,"height":198}}}},{"name":"招財進","attachments":{"進2":{"進":{"name":"fo_03","type":"mesh","uvs":[1,1,0,1,0,0,1,0],"triangles":[1,2,3,1,3,0],"vertices":[206,-325,-27,-325,-27,-112,206,-112],"hull":4,"edges":[0,2,2,4,4,6,0,6],"width":233,"height":213}},"招財進_財寶":{"招財進_財寶":{"name":"pot_03","type":"mesh","uvs":[1,1,0,1,0,0,1,0],"triangles":[1,2,3,1,3,0],"vertices":[366,-54,-407,-54,-407,131,366,131],"hull":4,"edges":[0,2,2,4,4,6,0,6],"width":773,"height":185}},"招":{"招":{"name":"fo_1","type":"mesh","path":"fo_01","uvs":[1,1,0,1,0,0,1,0],"triangles":[1,2,3,1,3,0],"vertices":[-238,-267,-453,-267,-453,-69,-238,-69],"hull":4,"edges":[0,2,2,4,4,6,0,6],"width":215,"height":198}},"財":{"財":{"name":"fo_2","type":"mesh","path":"fo_02","uvs":[1,1,0,1,0,0,1,0],"triangles":[1,2,3,1,3,0],"vertices":[-26,-325,-258,-325,-258,-111,-26,-111],"hull":4,"edges":[0,2,2,4,4,6,0,6],"width":232,"height":214}},"招財進_財寶2":{"招財進_財寶":{"name":"pot_03","type":"mesh","uvs":[1,1,0,1,0,0,1,0],"triangles":[1,2,3,1,3,0],"vertices":[366,-54,-407,-54,-407,131,366,131],"hull":4,"edges":[0,2,2,4,4,6,0,6],"width":773,"height":185}},"財2":{"財":{"name":"fo_2","type":"mesh","path":"fo_02","uvs":[1,1,0,1,0,0,1,0],"triangles":[1,2,3,1,3,0],"vertices":[-26,-325,-258,-325,-258,-111,-26,-111],"hull":4,"edges":[0,2,2,4,4,6,0,6],"width":232,"height":214}},"進":{"進":{"name":"fo_03","type":"mesh","uvs":[1,1,0,1,0,0,1,0],"triangles":[1,2,3,1,3,0],"vertices":[206,-325,-27,-325,-27,-112,206,-112],"hull":4,"edges":[0,2,2,4,4,6,0,6],"width":233,"height":213}},"招2":{"招":{"name":"fo_1","type":"mesh","path":"fo_01","uvs":[1,1,0,1,0,0,1,0],"triangles":[1,2,3,1,3,0],"vertices":[-238,-267,-453,-267,-453,-69,-238,-69],"hull":4,"edges":[0,2,2,4,4,6,0,6],"width":215,"height":198}}}},{"name":"招財進寶","attachments":{"進2":{"進":{"name":"fo_3","type":"mesh","path":"fo_03","uvs":[1,1,0,1,0,0,1,0],"triangles":[1,2,3,1,3,0],"vertices":[206,-325,-27,-325,-27,-112,206,-112],"hull":4,"edges":[0,2,2,4,4,6,0,6],"width":233,"height":213}},"招財進寶_財寶_LIG":{"招財進寶_財寶":{"name":"pot_04","type":"mesh","uvs":[1,1,0,1,0,0,1,0],"triangles":[1,2,3,1,3,0],"vertices":[379,-54,-413,-54,-413,313,379,313],"hull":4,"edges":[0,2,2,4,4,6,0,6],"width":792,"height":367}},"招":{"招":{"name":"fo_1","type":"mesh","path":"fo_01","uvs":[1,1,0,1,0,0,1,0],"triangles":[1,2,3,1,3,0],"vertices":[-238,-267,-453,-267,-453,-69,-238,-69],"hull":4,"edges":[0,2,2,4,4,6,0,6],"width":215,"height":198}},"財":{"財":{"name":"fo_2","type":"mesh","path":"fo_02","uvs":[1,1,0,1,0,0,1,0],"triangles":[1,2,3,1,3,0],"vertices":[-26,-325,-258,-325,-258,-111,-26,-111],"hull":4,"edges":[0,2,2,4,4,6,0,6],"width":232,"height":214}},"招財進寶_財寶":{"招財進寶_財寶":{"name":"pot_04","type":"mesh","uvs":[1,1,0,1,0,0,1,0],"triangles":[1,2,3,1,3,0],"vertices":[379,-54,-413,-54,-413,313,379,313],"hull":4,"edges":[0,2,2,4,4,6,0,6],"width":792,"height":367}},"財2":{"財":{"name":"fo_2","type":"mesh","path":"fo_02","uvs":[1,1,0,1,0,0,1,0],"triangles":[1,2,3,1,3,0],"vertices":[-26,-325,-258,-325,-258,-111,-26,-111],"hull":4,"edges":[0,2,2,4,4,6,0,6],"width":232,"height":214}},"進":{"進":{"name":"fo_3","type":"mesh","path":"fo_03","uvs":[1,1,0,1,0,0,1,0],"triangles":[1,2,3,1,3,0],"vertices":[206,-325,-27,-325,-27,-112,206,-112],"hull":4,"edges":[0,2,2,4,4,6,0,6],"width":233,"height":213}},"寶":{"寶":{"name":"fo_04","type":"mesh","uvs":[1,1,0,1,0,0,1,0],"triangles":[1,2,3,1,3,0],"vertices":[401,-267,186,-267,186,-69,401,-69],"hull":4,"edges":[0,2,2,4,4,6,0,6],"width":215,"height":198}},"招2":{"招":{"name":"fo_1","type":"mesh","path":"fo_01","uvs":[1,1,0,1,0,0,1,0],"triangles":[1,2,3,1,3,0],"vertices":[-238,-267,-453,-267,-453,-69,-238,-69],"hull":4,"edges":[0,2,2,4,4,6,0,6],"width":215,"height":198}},"寶2":{"寶":{"name":"fo_04","type":"mesh","uvs":[1,1,0,1,0,0,1,0],"triangles":[1,2,3,1,3,0],"vertices":[401,-267,186,-267,186,-69,401,-69],"hull":4,"edges":[0,2,2,4,4,6,0,6],"width":215,"height":198}}}}],"animations":{"animation":{"slots":{"招財_財寶2":{"color":[{"color":"ffffff00","curve":0.25,"c3":0.75},{"time":0.6667,"color":"ffffff8b","curve":0.25,"c3":0.75},{"time":1.3333,"color":"ffffff00"}],"attachment":[{"name":"招財_財寶"}]},"LigDot01":{"color":[{"color":"ffffff00","curve":"stepped"},{"time":0.1667,"color":"ffffff00","curve":0.25,"c3":0.75},{"time":0.5,"color":"ffffff80","curve":0.25,"c3":0.75},{"time":0.8333,"color":"ffffff00"}],"attachment":[{"name":"LigDot01"}]},"進2":{"color":[{"color":"ffffff00"},{"time":0.6667,"color":"ffffff8b"},{"time":1.3333,"color":"ffffff00"}],"attachment":[{"name":"進"}]},"LigDot_Seq":{"attachment":[{"time":0.0333,"name":"光點_02/3_00001"},{"time":0.1,"name":"光點_02/3_00002"},{"time":0.1333,"name":"光點_02/3_00003"},{"time":0.1667,"name":"光點_02/3_00004"},{"time":0.2333,"name":"光點_02/3_00005"},{"time":0.2667,"name":"光點_02/3_00006"},{"time":0.3,"name":"光點_02/3_00007"},{"time":0.3667,"name":"光點_02/3_00008"},{"time":0.4,"name":"光點_02/3_00009"},{"time":0.4333,"name":"光點_02/3_00010"},{"time":0.5,"name":"光點_02/3_00011"},{"time":0.5333,"name":"光點_02/3_00012"},{"time":0.5667,"name":"光點_02/3_00013"},{"time":0.6333,"name":"光點_02/3_00014"},{"time":0.6667,"name":"光點_02/3_00015"},{"time":0.7,"name":"光點_02/3_00016"},{"time":0.7667,"name":"光點_02/3_00017"},{"time":0.8,"name":"光點_02/3_00018"},{"time":0.8667,"name":"光點_02/3_00019"},{"time":0.9,"name":"光點_02/3_00020"},{"time":0.9333,"name":"光點_02/3_00021"},{"time":1,"name":"光點_02/3_00022"},{"time":1.0333,"name":"光點_02/3_00023"},{"time":1.0667,"name":"光點_02/3_00024"},{"time":1.1333,"name":"光點_02/3_00025"},{"time":1.1667,"name":"光點_02/3_00026"},{"time":1.2,"name":"光點_02/3_00027"},{"time":1.2667,"name":"光點_02/3_00028"},{"time":1.3,"name":"光點_02/3_00029"},{"time":1.3333,"name":null}]},"寶2":{"color":[{"color":"ffffff00"},{"time":0.6667,"color":"ffffff8b"},{"time":1.3333,"color":"ffffff00"}],"attachment":[{"name":"寶"}]},"招財進_財寶2":{"color":[{"color":"ffffff00","curve":0.25,"c3":0.75},{"time":0.6667,"color":"ffffff8b","curve":0.25,"c3":0.75},{"time":1.3333,"color":"ffffff00"}],"attachment":[{"name":"招財進_財寶"}]},"LigDot2":{"color":[{"color":"ffffff00","curve":"stepped"},{"time":0.5,"color":"ffffff00","curve":0.25,"c3":0.75},{"time":0.8333,"color":"ffffff80","curve":0.25,"c3":0.75},{"time":1.1667,"color":"ffffff00"}],"attachment":[{"name":"LigDot01"}]},"財2":{"color":[{"color":"ffffff00"},{"time":0.6667,"color":"ffffff8b"},{"time":1.3333,"color":"ffffff00"}],"attachment":[{"name":"財"}]},"招2":{"color":[{"color":"ffffff00"},{"time":0.6667,"color":"ffffff8b"},{"time":1.3333,"color":"ffffff00"}],"attachment":[{"name":"招"}]},"LigDot1":{"color":[{"color":"ffffff00","curve":"stepped"},{"time":0.3333,"color":"ffffff00","curve":0.25,"c3":0.75},{"time":0.6667,"color":"ffffff80","curve":0.25,"c3":0.75},{"time":1,"color":"ffffff00"}],"attachment":[{"name":"LigDot01"}]},"pot_Lig":{"color":[{"color":"ffffff00","curve":0.25,"c3":0.75},{"time":0.6667,"color":"ffffff7e","curve":0.25,"c3":0.75},{"time":1.3333,"color":"ffffff00"}],"attachment":[{"name":"pot_05"}]},"all_Lig":{"color":[{"color":"ffffff00","curve":0.25,"c3":0.75},{"time":0.6667,"color":"ffffff42","curve":0.25,"c3":0.75},{"time":1.3333,"color":"ffffff00"}],"attachment":[{"name":"all"}]},"LigDot3":{"color":[{"color":"ffffff00","curve":"stepped"},{"time":0.6667,"color":"ffffff00","curve":0.25,"c3":0.75},{"time":1,"color":"ffffff80","curve":0.25,"c3":0.75},{"time":1.3333,"color":"ffffff00"}],"attachment":[{"name":"LigDot01"}]},"招財進寶_財寶_LIG":{"color":[{"color":"ffffff00","curve":0.25,"c3":0.75},{"time":0.6667,"color":"ffffff8b","curve":0.25,"c3":0.75},{"time":1.3333,"color":"ffffff00"}],"attachment":[{"name":"招財進寶_財寶"}]},"招_財寶2":{"color":[{"color":"ffffff00","curve":0.25,"c3":0.75},{"time":0.6667,"color":"ffffff8b","curve":0.25,"c3":0.75},{"time":1.3333,"color":"ffffff00"}],"attachment":[{"name":"招_財寶"}]}},"bones":{"LigDot01":{"rotate":[{"time":0.1667,"curve":0.25,"c3":0.75},{"time":0.8333,"angle":-45}],"translate":[{},{"time":0.1667,"x":-218.35,"y":-331.06}],"scale":[{},{"time":0.1667,"x":2.636,"y":2.636}]},"LigDot1":{"rotate":[{"time":0.3333,"curve":0.25,"c3":0.75},{"time":1,"angle":-45}],"translate":[{},{"time":0.3333,"x":-486.7,"y":-66.26}],"scale":[{},{"time":0.3333,"x":2.213,"y":2.213}]},"LigDot2":{"rotate":[{"time":0.5,"curve":0.25,"c3":0.75},{"time":1.1667,"angle":-45}],"translate":[{},{"time":0.5,"x":467.74,"y":-66.26}],"scale":[{},{"time":0.5,"x":3.682,"y":3.682}]},"LigDot3":{"rotate":[{"time":0.6667,"curve":0.25,"c3":0.75},{"time":1.3333,"angle":-45}],"translate":[{},{"time":0.6667,"x":-18.97,"y":-112.55}],"scale":[{},{"time":0.6667,"x":1.861,"y":1.861}]}}},"animation2":{"slots":{"cover_01":{"color":[{"color":"ffffff00"},{"time":0.1667,"color":"ffffffff"}],"attachment":[{"name":"cover_01"}]},"cover_02":{"color":[{"color":"ffffff00"},{"time":0.1667,"color":"ffffffff"}],"attachment":[{"name":"cover_02"}]},"cover_Lig":{"color":[{"color":"ffffff00"},{"time":0.1667,"color":"ffffffff"}],"attachment":[{"name":"cover_01"}]},"cover_2":{"color":[{"color":"ffffff00"},{"time":0.1667,"color":"ffffffff"}],"attachment":[{"name":"cover_02"}]}},"bones":{"cover_01":{"translate":[{"y":486.87,"curve":0.25,"c4":0.71},{"time":0.4,"y":-34.66,"curve":0.25,"c3":0.75},{"time":0.5667}]},"All":{"translate":[{"time":0.3333},{"time":0.4333,"y":-41.29},{"time":0.6}],"scale":[{"time":0.3333},{"time":0.4333,"y":0.9},{"time":0.6}]},"cover_Lig":{"translate":[{"y":486.87,"curve":0.25,"c4":0.71},{"time":0.4,"y":-34.66,"curve":0.25,"c3":0.75},{"time":0.5667}]}}},"animation3":{"slots":{"招財_財寶2":{"color":[{"color":"ffffff00","curve":0.25,"c3":0.75},{"time":0.3333,"color":"ffffff82","curve":"stepped"},{"time":1,"color":"ffffff82","curve":0.25,"c3":0.75},{"time":1.3333,"color":"ffffff00"}],"attachment":[{"name":"招財_財寶"}]},"cover_01":{"color":[{"time":0.5667,"color":"ffffffff"},{"time":0.7,"color":"ffffff00"}],"attachment":[{"name":"cover_01"}]},"cover_02":{"color":[{"time":0.5667,"color":"ffffffff"},{"time":0.7,"color":"ffffff00"}],"attachment":[{"name":"cover_02"}]},"cover_2":{"color":[{"color":"ffffff00","curve":0.25,"c3":0.75},{"time":0.3,"color":"ffffffbf","curve":"stepped"},{"time":0.5667,"color":"ffffffbf","curve":0.25,"c3":0.75},{"time":0.7,"color":"ffffff00"}],"attachment":[{"name":"cover_02"}]},"寶2":{"color":[{"color":"ffffff00"},{"time":0.3333,"color":"ffffff82","curve":"stepped"},{"time":1,"color":"ffffff82"},{"time":1.3333,"color":"ffffff00"}],"attachment":[{"name":"寶"}]},"招財進_財寶2":{"color":[{"color":"ffffff00","curve":0.25,"c3":0.75},{"time":0.3333,"color":"ffffff82","curve":"stepped"},{"time":1,"color":"ffffff82","curve":0.25,"c3":0.75},{"time":1.3333,"color":"ffffff00"}],"attachment":[{"name":"招財進_財寶"}]},"財2":{"color":[{"color":"ffffff00"},{"time":0.3333,"color":"ffffff82","curve":"stepped"},{"time":1,"color":"ffffff82"},{"time":1.3333,"color":"ffffff00"}],"attachment":[{"name":"財"}]},"招2":{"color":[{"color":"ffffff00"},{"time":0.3333,"color":"ffffff82","curve":"stepped"},{"time":1,"color":"ffffff82"},{"time":1.3333,"color":"ffffff00"}],"attachment":[{"name":"招"}]},"cover_Lig":{"color":[{"color":"ffffff00","curve":0.25,"c3":0.75},{"time":0.3,"color":"ffffffbf","curve":"stepped"},{"time":0.5667,"color":"ffffffbf","curve":0.25,"c3":0.75},{"time":0.7,"color":"ffffff00"}],"attachment":[{"name":"cover_01"}]},"pot_Lig":{"color":[{"color":"ffffff00","curve":0.25,"c3":0.75},{"time":0.3333,"color":"ffffff8b","curve":"stepped"},{"time":1,"color":"ffffff8b","curve":0.25,"c3":0.75},{"time":1.3333,"color":"ffffff00"}],"attachment":[{"name":"pot_05"}]},"Explo_SeqA":{"attachment":[{"name":"火焰爆炸合/Explo_A_00002"},{"time":0.0333,"name":"火焰爆炸合/Explo_A_00004"},{"time":0.0667,"name":"火焰爆炸合/Explo_A_00005"},{"time":0.1,"name":"火焰爆炸合/Explo_A_00006"},{"time":0.1333,"name":"火焰爆炸合/Explo_A_00008"},{"time":0.1667,"name":"火焰爆炸合/Explo_A_00010"},{"time":0.2,"name":"火焰爆炸合/Explo_A_00012"},{"time":0.2333,"name":"火焰爆炸合/Explo_A_00013"},{"time":0.2667,"name":"火焰爆炸合/Explo_A_00014"},{"time":0.3,"name":"火焰爆炸合/Explo_A_00016"},{"time":0.3333,"name":"火焰爆炸合/Explo_A_00018"},{"time":0.3667,"name":"火焰爆炸合/Explo_A_00020"},{"time":0.4,"name":"火焰爆炸合/Explo_A_00021"},{"time":0.4333,"name":"火焰爆炸合/Explo_A_00022"},{"time":0.4667,"name":"火焰爆炸合/Explo_A_00024"},{"time":0.5,"name":"火焰爆炸合/Explo_A_00026"},{"time":0.5333,"name":"火焰爆炸合/Explo_A_00027"},{"time":0.5667,"name":"火焰爆炸合/Explo_A_00028"},{"time":0.6,"name":"火焰爆炸合/Explo_A_00029"},{"time":0.6333,"name":"火焰爆炸合/Explo_A_00030"},{"time":0.6667,"name":"火焰爆炸合/Explo_A_00031"},{"time":0.7,"name":"火焰爆炸合/Explo_A_00032"},{"time":0.7333,"name":"火焰爆炸合/Explo_A_00033"},{"time":0.7667,"name":"火焰爆炸合/Explo_A_00034"},{"time":0.8,"name":"火焰爆炸合/Explo_A_00035"},{"time":0.8333,"name":"火焰爆炸合/Explo_A_00036"},{"time":0.8667,"name":"火焰爆炸合/Explo_A_00037"},{"time":0.9,"name":"火焰爆炸合/Explo_A_00038"},{"time":0.9333,"name":"火焰爆炸合/Explo_A_00039"},{"time":0.9667,"name":"火焰爆炸合/Explo_A_00040"},{"time":1,"name":"火焰爆炸合/Explo_A_00041"},{"time":1.0333,"name":"火焰爆炸合/Explo_A_00043"},{"time":1.0667,"name":"火焰爆炸合/Explo_A_00045"},{"time":1.1,"name":"火焰爆炸合/Explo_A_00047"},{"time":1.1333,"name":"火焰爆炸合/Explo_A_00049"},{"time":1.1667,"name":"火焰爆炸合/Explo_A_00051"},{"time":1.2,"name":null}]},"Explo_SeqB":{"color":[{"time":0.5,"color":"ffffffb6","curve":"stepped"},{"time":0.7333,"color":"ffffffb6"},{"time":0.9,"color":"ffffff1a"}],"attachment":[{"time":0.5333,"name":"爆炸_05/001"},{"time":0.5667,"name":"爆炸_05/002"},{"time":0.6,"name":"爆炸_05/003"},{"time":0.6333,"name":"爆炸_05/004"},{"time":0.7,"name":"爆炸_05/005"},{"time":0.7333,"name":"爆炸_05/006"},{"time":0.7667,"name":"爆炸_05/007"},{"time":0.8333,"name":"爆炸_05/008"},{"time":0.8667,"name":"爆炸_05/009"},{"time":0.9,"name":"爆炸_05/010"},{"time":0.9667,"name":null}]},"進2":{"color":[{"color":"ffffff00"},{"time":0.3333,"color":"ffffff82","curve":"stepped"},{"time":1,"color":"ffffff82"},{"time":1.3333,"color":"ffffff00"}],"attachment":[{"name":"進"}]},"招財進寶_財寶_LIG":{"color":[{"color":"ffffff00","curve":0.25,"c3":0.75},{"time":0.3333,"color":"ffffff82","curve":"stepped"},{"time":1,"color":"ffffff82","curve":0.25,"c3":0.75},{"time":1.3333,"color":"ffffff00"}],"attachment":[{"name":"招財進寶_財寶"}]},"招_財寶2":{"color":[{"color":"ffffff00","curve":0.25,"c3":0.75},{"time":0.3333,"color":"ffffff82","curve":"stepped"},{"time":1,"color":"ffffff82","curve":0.25,"c3":0.75},{"time":1.3333,"color":"ffffff00"}],"attachment":[{"name":"招_財寶"}]}},"bones":{"cover_01":{"translate":[{"time":0.4667,"curve":0,"c2":0.31,"c3":0.75},{"time":0.7,"y":635.2}]},"All":{"rotate":[{"curve":0.25,"c3":0.75},{"time":0.0667,"angle":-4.17,"curve":0.25,"c3":0.75},{"time":0.1333,"angle":3.61,"curve":0.25,"c3":0.75},{"time":0.2333,"angle":-6.86,"curve":0.25,"c3":0.75},{"time":0.3,"curve":0.25,"c3":0.75},{"time":0.3667,"angle":3.61,"curve":0.25,"c3":0.75},{"time":0.4667}],"translate":[{"curve":0.25,"c3":0.75},{"time":0.4667,"y":-40.42,"curve":0.25,"c3":0.75},{"time":0.7,"y":130.23,"curve":"stepped"},{"time":0.7667,"y":130.23,"curve":0.25,"c3":0.75},{"time":1,"y":-40.42,"curve":0.25,"c3":0.75},{"time":1.1}],"scale":[{"curve":0.25,"c3":0.75},{"time":0.4667,"y":0.9,"curve":0.25,"c3":0.75},{"time":0.7,"x":1.123,"y":1.123,"curve":"stepped"},{"time":0.7667,"x":1.123,"y":1.123,"curve":0.25,"c3":0.75},{"time":1,"y":0.9,"curve":0.25,"c3":0.75},{"time":1.1}]},"Explo_SeqA":{"translate":[{"y":94.9,"curve":"stepped"},{"time":0.4667,"y":94.9},{"time":0.5,"y":324.23},{"time":0.5667,"y":371.68},{"time":0.6667,"y":425.82}],"scale":[{"x":7.687,"y":7.687}]},"Explo_SeqB":{"translate":[{"time":0.5,"y":42.97},{"time":0.7333,"y":371.75}],"scale":[{"time":0.5,"x":4.946,"y":4.946},{"time":0.7333,"x":6.792,"y":6.792}]},"cover_Lig":{"translate":[{"time":0.4667,"curve":0,"c2":0.31,"c3":0.75},{"time":0.7,"y":635.2}]}}}}}